{"get":"players","parameters":{"id":"34711","season":"2021"},"errors":[],"results":1,"paging":{"current":1,"total":1},"response":[{"player":{"id":34711,"name":"A. Taggart","firstname":"Adam Jake","lastname":"Taggart","age":28,"birth":{"date":"1993-06-02","place":"Perth","country":"Australia"},"nationality":"Australia","height":"183 cm","weight":"69 kg","injured":false,"photo":"https:\/\/media.api-sports.io\/football\/players\/34711.png"},"statistics":[{"team":{"id":291,"name":"Cerezo Osaka","logo":"https:\/\/media.api-sports.io\/football\/teams\/291.png"},"league":{"id":98,"name":"J. League Div.1","country":"Japan","logo":"https:\/\/media.api-sports.io\/football\/leagues\/98.png","flag":"https:\/\/media.api-sports.io\/flags\/jp.svg","season":2021},"games":{"appearences":12,"lineups":8,"minutes":644,"number":null,"position":"Attacker","rating":"6.625000","captain":false},"substitutes":{"in":4,"out":9,"bench":4},"shots":{"total":20,"on":7},"goals":{"total":1,"conceded":0,"assists":null,"saves":null},"passes":{"total":128,"key":5,"accuracy":7},"tackles":{"total":5,"blocks":null,"interceptions":1},"duels":{"total":53,"won":21},"dribbles":{"attempts":4,"success":1,"past":null},"fouls":{"drawn":7,"committed":6},"cards":{"yellow":0,"yellowred":0,"red":0},"penalty":{"won":null,"commited":null,"scored":0,"missed":0,"saved":null}},{"team":{"id":291,"name":"Cerezo Osaka","logo":"https:\/\/media.api-sports.io\/football\/teams\/291.png"},"league":{"id":101,"name":"J-League Cup","country":"Japan","logo":"https:\/\/media.api-sports.io\/football\/leagues\/101.png","flag":"https:\/\/media.api-sports.io\/flags\/jp.svg","season":2021},"games":{"appearences":3,"lineups":3,"minutes":195,"number":null,"position":"Attacker","rating":null,"captain":false},"substitutes":{"in":0,"out":3,"bench":0},"shots":{"total":null,"on":null},"goals":{"total":1,"conceded":null,"assists":null,"saves":null},"passes":{"total":null,"key":null,"accuracy":null},"tackles":{"total":null,"blocks":null,"interceptions":null},"duels":{"total":null,"won":null},"dribbles":{"attempts":null,"success":null,"past":null},"fouls":{"drawn":null,"committed":null},"cards":{"yellow":0,"yellowred":0,"red":0},"penalty":{"won":null,"commited":null,"scored":null,"missed":null,"saved":null}},{"team":{"id":291,"name":"Cerezo Osaka","logo":"https:\/\/media.api-sports.io\/football\/teams\/291.png"},"league":{"id":17,"name":"AFC Champions League","country":"World","logo":"https:\/\/media.api-sports.io\/football\/leagues\/17.png","flag":null,"season":2021},"games":{"appearences":4,"lineups":3,"minutes":216,"number":null,"position":"Attacker","rating":"6.875000","captain":false},"substitutes":{"in":1,"out":4,"bench":1},"shots":{"total":7,"on":2},"goals":{"total":1,"conceded":0,"assists":null,"saves":null},"passes":{"total":46,"key":3,"accuracy":9},"tackles":{"total":1,"blocks":null,"interceptions":null},"duels":{"total":14,"won":6},"dribbles":{"attempts":3,"success":2,"past":null},"fouls":{"drawn":null,"committed":2},"cards":{"yellow":0,"yellowred":0,"red":0},"penalty":{"won":null,"commited":null,"scored":0,"missed":0,"saved":null}}]}]}