{"get":"players","parameters":{"id":"156477","season":"2021"},"errors":[],"results":1,"paging":{"current":1,"total":1},"response":[{"player":{"id":156477,"name":"R. Cherki","firstname":"Rayan Mathis","lastname":"Cherki","age":18,"birth":{"date":"2003-08-17","place":"Lyon","country":"France"},"nationality":"France","height":"176 cm","weight":"71 kg","injured":false,"photo":"https:\/\/media.api-sports.io\/football\/players\/156477.png"},"statistics":[{"team":{"id":80,"name":"Lyon","logo":"https:\/\/media.api-sports.io\/football\/teams\/80.png"},"league":{"id":61,"name":"Ligue 1","country":"France","logo":"https:\/\/media.api-sports.io\/football\/leagues\/61.png","flag":"https:\/\/media.api-sports.io\/flags\/fr.svg","season":2021},"games":{"appearences":8,"lineups":2,"minutes":187,"number":null,"position":"Attacker","rating":"6.542857","captain":false},"substitutes":{"in":6,"out":2,"bench":11},"shots":{"total":5,"on":2},"goals":{"total":0,"conceded":0,"assists":null,"saves":null},"passes":{"total":100,"key":4,"accuracy":9},"tackles":{"total":null,"blocks":null,"interceptions":null},"duels":{"total":31,"won":13},"dribbles":{"attempts":15,"success":6,"past":null},"fouls":{"drawn":7,"committed":2},"cards":{"yellow":0,"yellowred":0,"red":0},"penalty":{"won":null,"commited":null,"scored":0,"missed":0,"saved":null}},{"team":{"id":80,"name":"Lyon","logo":"https:\/\/media.api-sports.io\/football\/teams\/80.png"},"league":{"id":3,"name":"UEFA Europa League","country":"World","logo":"https:\/\/media.api-sports.io\/football\/leagues\/3.png","flag":null,"season":2021},"games":{"appearences":2,"lineups":1,"minutes":107,"number":null,"position":"Attacker","rating":"7.250000","captain":false},"substitutes":{"in":1,"out":1,"bench":3},"shots":{"total":2,"on":1},"goals":{"total":0,"conceded":0,"assists":1,"saves":null},"passes":{"total":58,"key":4,"accuracy":23},"tackles":{"total":1,"blocks":null,"interceptions":2},"duels":{"total":14,"won":7},"dribbles":{"attempts":9,"success":3,"past":null},"fouls":{"drawn":3,"committed":null},"cards":{"yellow":0,"yellowred":0,"red":0},"penalty":{"won":null,"commited":null,"scored":0,"missed":0,"saved":null}}]}]}