{"get":"players","parameters":{"team":"85","season":"2021"},"errors":[],"results":20,"paging":{"current":1,"total":3},"response":[{"player":{"id":530,"name":"M. Bakker","firstname":"Mitchel","lastname":"Bakker","age":21,"birth":{"date":"2000-06-20","place":"Purmerend","country":"Netherlands"},"nationality":"Netherlands","height":"185 cm","weight":"85 kg","injured":false,"photo":"https:\/\/media.api-sports.io\/football\/players\/530.png"},"statistics":[{"team":{"id":85,"name":"Paris Saint Germain","logo":"https:\/\/media.api-sports.io\/football\/teams\/85.png"},"league":{"id":null,"name":"Club Friendlies","country":null,"logo":null,"flag":null,"season":"2021"},"games":{"appearences":0,"lineups":0,"minutes":0,"number":null,"position":"Defender","rating":null,"captain":false},"substitutes":{"in":0,"out":0,"bench":0},"shots":{"total":null,"on":null},"goals":{"total":0,"conceded":null,"assists":null,"saves":null},"passes":{"total":null,"key":null,"accuracy":null},"tackles":{"total":null,"blocks":null,"interceptions":null},"duels":{"total":null,"won":null},"dribbles":{"attempts":null,"success":null,"past":null},"fouls":{"drawn":null,"committed":null},"cards":{"yellow":0,"yellowred":0,"red":0},"penalty":{"won":null,"commited":null,"scored":null,"missed":null,"saved":null}}]},{"player":{"id":769,"name":"A. Florenzi","firstname":"Alessandro","lastname":"Florenzi","age":30,"birth":{"date":"1991-03-11","place":"Roma","country":"Italy"},"nationality":"Italy","height":"173 cm","weight":"67 kg","injured":false,"photo":"https:\/\/media.api-sports.io\/football\/players\/769.png"},"statistics":[{"team":{"id":85,"name":"Paris Saint Germain","logo":"https:\/\/media.api-sports.io\/football\/teams\/85.png"},"league":{"id":null,"name":"Club Friendlies","country":null,"logo":null,"flag":null,"season":"2021"},"games":{"appearences":0,"lineups":0,"minutes":0,"number":null,"position":"Defender","rating":null,"captain":false},"substitutes":{"in":0,"out":0,"bench":0},"shots":{"total":null,"on":null},"goals":{"total":0,"conceded":null,"assists":null,"saves":null},"passes":{"total":null,"key":null,"accuracy":null},"tackles":{"total":null,"blocks":null,"interceptions":null},"duels":{"total":null,"won":null},"dribbles":{"attempts":null,"success":null,"past":null},"fouls":{"drawn":null,"committed":null},"cards":{"yellow":0,"yellowred":0,"red":0},"penalty":{"won":null,"commited":null,"scored":null,"missed":null,"saved":null}}]},{"player":{"id":877,"name":"M. Kean","firstname":"Moise Bioty","lastname":"Kean","age":21,"birth":{"date":"2000-02-28","place":"Vercelli","country":"Italy"},"nationality":"Italy","height":"182 cm","weight":"67 kg","injured":false,"photo":"https:\/\/media.api-sports.io\/football\/players\/877.png"},"statistics":[{"team":{"id":85,"name":"Paris Saint Germain","logo":"https:\/\/media.api-sports.io\/football\/teams\/85.png"},"league":{"id":null,"name":"Club Friendlies","country":null,"logo":null,"flag":null,"season":"2021"},"games":{"appearences":0,"lineups":0,"minutes":0,"number":null,"position":"Attacker","rating":null,"captain":false},"substitutes":{"in":0,"out":0,"bench":0},"shots":{"total":null,"on":null},"goals":{"total":0,"conceded":null,"assists":null,"saves":null},"passes":{"total":null,"key":null,"accuracy":null},"tackles":{"total":null,"blocks":null,"interceptions":null},"duels":{"total":null,"won":null},"dribbles":{"attempts":null,"success":null,"past":null},"fouls":{"drawn":null,"committed":null},"cards":{"yellow":0,"yellowred":0,"red":0},"penalty":{"won":null,"commited":null,"scored":null,"missed":null,"saved":null}}]},{"player":{"id":1622,"name":"G. Donnarumma","firstname":"Gianluigi","lastname":"Donnarumma","age":22,"birth":{"date":"1999-02-25","place":"Castellammare di Stabia","country":"Italy"},"nationality":"Italy","height":"196 cm","weight":"90 kg","injured":false,"photo":"https:\/\/media.api-sports.io\/football\/players\/1622.png"},"statistics":[{"team":{"id":85,"name":"Paris Saint Germain","logo":"https:\/\/media.api-sports.io\/football\/teams\/85.png"},"league":{"id":61,"name":"Ligue 1","country":"France","logo":"https:\/\/media.api-sports.io\/football\/leagues\/61.png","flag":"https:\/\/media.api-sports.io\/flags\/fr.svg","season":2021},"games":{"appearences":5,"lineups":5,"minutes":450,"number":null,"position":"Goalkeeper","rating":"6.780000","captain":false},"substitutes":{"in":0,"out":0,"bench":5},"shots":{"total":null,"on":null},"goals":{"total":0,"conceded":5,"assists":null,"saves":11},"passes":{"total":113,"key":null,"accuracy":20},"tackles":{"total":null,"blocks":null,"interceptions":null},"duels":{"total":1,"won":1},"dribbles":{"attempts":null,"success":null,"past":null},"fouls":{"drawn":1,"committed":null},"cards":{"yellow":1,"yellowred":0,"red":0},"penalty":{"won":null,"commited":null,"scored":0,"missed":0,"saved":0}},{"team":{"id":85,"name":"Paris Saint Germain","logo":"https:\/\/media.api-sports.io\/football\/teams\/85.png"},"league":{"id":2,"name":"UEFA Champions League","country":"World","logo":"https:\/\/media.api-sports.io\/football\/leagues\/2.png","flag":null,"season":2021},"games":{"appearences":2,"lineups":2,"minutes":180,"number":null,"position":"Goalkeeper","rating":"8.150000","captain":false},"substitutes":{"in":0,"out":0,"bench":2},"shots":{"total":null,"on":null},"goals":{"total":0,"conceded":2,"assists":null,"saves":10},"passes":{"total":58,"key":null,"accuracy":22},"tackles":{"total":null,"blocks":null,"interceptions":null},"duels":{"total":null,"won":null},"dribbles":{"attempts":null,"success":null,"past":null},"fouls":{"drawn":null,"committed":null},"cards":{"yellow":1,"yellowred":0,"red":0},"penalty":{"won":null,"commited":null,"scored":0,"missed":0,"saved":0}},{"team":{"id":85,"name":"Paris Saint Germain","logo":"https:\/\/media.api-sports.io\/football\/teams\/85.png"},"league":{"id":null,"name":"Club Friendlies","country":null,"logo":null,"flag":null,"season":"2021"},"games":{"appearences":0,"lineups":0,"minutes":0,"number":null,"position":"Goalkeeper","rating":null,"captain":false},"substitutes":{"in":0,"out":0,"bench":0},"shots":{"total":null,"on":null},"goals":{"total":0,"conceded":null,"assists":null,"saves":null},"passes":{"total":null,"key":null,"accuracy":null},"tackles":{"total":null,"blocks":null,"interceptions":null},"duels":{"total":null,"won":null},"dribbles":{"attempts":null,"success":null,"past":null},"fouls":{"drawn":null,"committed":null},"cards":{"yellow":0,"yellowred":0,"red":0},"penalty":{"won":null,"commited":null,"scored":null,"missed":null,"saved":null}}]},{"player":{"id":2056,"name":"Pablo Sarabia","firstname":"Pablo","lastname":"Sarabia Garc\u00eda","age":29,"birth":{"date":"1992-05-11","place":"Madrid","country":"Spain"},"nationality":"Spain","height":"174 cm","weight":"70 kg","injured":false,"photo":"https:\/\/media.api-sports.io\/football\/players\/2056.png"},"statistics":[{"team":{"id":85,"name":"Paris Saint Germain","logo":"https:\/\/media.api-sports.io\/football\/teams\/85.png"},"league":{"id":61,"name":"Ligue 1","country":"France","logo":"https:\/\/media.api-sports.io\/football\/leagues\/61.png","flag":"https:\/\/media.api-sports.io\/flags\/fr.svg","season":2021},"games":{"appearences":2,"lineups":0,"minutes":20,"number":null,"position":"Midfielder","rating":"7.300000","captain":false},"substitutes":{"in":2,"out":0,"bench":2},"shots":{"total":1,"on":1},"goals":{"total":1,"conceded":0,"assists":null,"saves":null},"passes":{"total":18,"key":null,"accuracy":13},"tackles":{"total":null,"blocks":null,"interceptions":null},"duels":{"total":4,"won":2},"dribbles":{"attempts":1,"success":1,"past":null},"fouls":{"drawn":1,"committed":1},"cards":{"yellow":1,"yellowred":0,"red":0},"penalty":{"won":null,"commited":null,"scored":0,"missed":0,"saved":null}},{"team":{"id":85,"name":"Paris Saint Germain","logo":"https:\/\/media.api-sports.io\/football\/teams\/85.png"},"league":{"id":2,"name":"UEFA Champions League","country":"World","logo":"https:\/\/media.api-sports.io\/football\/leagues\/2.png","flag":null,"season":2021},"games":{"appearences":0,"lineups":0,"minutes":0,"number":null,"position":"Midfielder","rating":"7.100000","captain":false},"substitutes":{"in":0,"out":0,"bench":0},"shots":{"total":3,"on":3},"goals":{"total":0,"conceded":0,"assists":null,"saves":null},"passes":{"total":72,"key":7,"accuracy":12},"tackles":{"total":5,"blocks":null,"interceptions":1},"duels":{"total":33,"won":14},"dribbles":{"attempts":7,"success":2,"past":null},"fouls":{"drawn":7,"committed":2},"cards":{"yellow":0,"yellowred":0,"red":0},"penalty":{"won":null,"commited":null,"scored":1,"missed":0,"saved":null}},{"team":{"id":85,"name":"Paris Saint Germain","logo":"https:\/\/media.api-sports.io\/football\/teams\/85.png"},"league":{"id":null,"name":"Club Friendlies","country":null,"logo":null,"flag":null,"season":"2021"},"games":{"appearences":0,"lineups":0,"minutes":0,"number":null,"position":"Midfielder","rating":null,"captain":false},"substitutes":{"in":0,"out":0,"bench":0},"shots":{"total":null,"on":null},"goals":{"total":0,"conceded":null,"assists":null,"saves":null},"passes":{"total":null,"key":null,"accuracy":null},"tackles":{"total":null,"blocks":null,"interceptions":null},"duels":{"total":null,"won":null},"dribbles":{"attempts":null,"success":null,"past":null},"fouls":{"drawn":null,"committed":null},"cards":{"yellow":0,"yellowred":0,"red":0},"penalty":{"won":null,"commited":null,"scored":null,"missed":null,"saved":null}}]},{"player":{"id":19014,"name":"Sergio Rico","firstname":"Sergio","lastname":"Rico Gonz\u00e1lez","age":28,"birth":{"date":"1993-09-01","place":"Sevilla","country":"Spain"},"nationality":"Spain","height":"194 cm","weight":"90 kg","injured":false,"photo":"https:\/\/media.api-sports.io\/football\/players\/19014.png"},"statistics":[{"team":{"id":85,"name":"Paris Saint Germain","logo":"https:\/\/media.api-sports.io\/football\/teams\/85.png"},"league":{"id":61,"name":"Ligue 1","country":"France","logo":"https:\/\/media.api-sports.io\/football\/leagues\/61.png","flag":"https:\/\/media.api-sports.io\/flags\/fr.svg","season":2021},"games":{"appearences":0,"lineups":0,"minutes":0,"number":null,"position":"Goalkeeper","rating":null,"captain":false},"substitutes":{"in":0,"out":0,"bench":3},"shots":{"total":null,"on":null},"goals":{"total":0,"conceded":0,"assists":null,"saves":null},"passes":{"total":null,"key":null,"accuracy":null},"tackles":{"total":null,"blocks":null,"interceptions":null},"duels":{"total":null,"won":null},"dribbles":{"attempts":null,"success":null,"past":null},"fouls":{"drawn":null,"committed":null},"cards":{"yellow":0,"yellowred":0,"red":0},"penalty":{"won":null,"commited":null,"scored":0,"missed":0,"saved":0}},{"team":{"id":85,"name":"Paris Saint Germain","logo":"https:\/\/media.api-sports.io\/football\/teams\/85.png"},"league":{"id":2,"name":"UEFA Champions League","country":"World","logo":"https:\/\/media.api-sports.io\/football\/leagues\/2.png","flag":null,"season":2021},"games":{"appearences":0,"lineups":0,"minutes":0,"number":null,"position":"Goalkeeper","rating":null,"captain":false},"substitutes":{"in":0,"out":0,"bench":0},"shots":{"total":null,"on":null},"goals":{"total":0,"conceded":null,"assists":null,"saves":null},"passes":{"total":null,"key":null,"accuracy":null},"tackles":{"total":null,"blocks":null,"interceptions":null},"duels":{"total":null,"won":null},"dribbles":{"attempts":null,"success":null,"past":null},"fouls":{"drawn":null,"committed":null},"cards":{"yellow":0,"yellowred":0,"red":0},"penalty":{"won":null,"commited":null,"scored":null,"missed":null,"saved":null}},{"team":{"id":85,"name":"Paris Saint Germain","logo":"https:\/\/media.api-sports.io\/football\/teams\/85.png"},"league":{"id":null,"name":"Club Friendlies","country":null,"logo":null,"flag":null,"season":"2021"},"games":{"appearences":1,"lineups":0,"minutes":44,"number":null,"position":"Goalkeeper","rating":null,"captain":false},"substitutes":{"in":1,"out":0,"bench":1},"shots":{"total":null,"on":null},"goals":{"total":0,"conceded":null,"assists":null,"saves":null},"passes":{"total":null,"key":null,"accuracy":null},"tackles":{"total":null,"blocks":null,"interceptions":null},"duels":{"total":null,"won":null},"dribbles":{"attempts":null,"success":null,"past":null},"fouls":{"drawn":null,"committed":null},"cards":{"yellow":0,"yellowred":0,"red":0},"penalty":{"won":null,"commited":null,"scored":null,"missed":null,"saved":null}}]},{"player":{"id":162018,"name":"B. Fadiga","firstname":"Bandiougou","lastname":"Fadiga","age":20,"birth":{"date":"2001-01-15","place":null,"country":"France"},"nationality":"France","height":null,"weight":null,"injured":false,"photo":"https:\/\/media.api-sports.io\/football\/players\/162018.png"},"statistics":[{"team":{"id":85,"name":"Paris Saint Germain","logo":"https:\/\/media.api-sports.io\/football\/teams\/85.png"},"league":{"id":61,"name":"Ligue 1","country":"France","logo":"https:\/\/media.api-sports.io\/football\/leagues\/61.png","flag":"https:\/\/media.api-sports.io\/flags\/fr.svg","season":2021},"games":{"appearences":null,"lineups":null,"minutes":null,"number":null,"position":"Midfielder","rating":null,"captain":false},"substitutes":{"in":null,"out":null,"bench":null},"shots":{"total":null,"on":null},"goals":{"total":null,"conceded":null,"assists":null,"saves":null},"passes":{"total":null,"key":null,"accuracy":null},"tackles":{"total":null,"blocks":null,"interceptions":null},"duels":{"total":null,"won":null},"dribbles":{"attempts":null,"success":null,"past":null},"fouls":{"drawn":null,"committed":null},"cards":{"yellow":null,"yellowred":null,"red":null},"penalty":{"won":null,"commited":null,"scored":null,"missed":null,"saved":null}},{"team":{"id":85,"name":"Paris Saint Germain","logo":"https:\/\/media.api-sports.io\/football\/teams\/85.png"},"league":{"id":null,"name":"Club Friendlies","country":null,"logo":null,"flag":null,"season":"2021"},"games":{"appearences":5,"lineups":1,"minutes":171,"number":null,"position":"Midfielder","rating":null,"captain":false},"substitutes":{"in":4,"out":1,"bench":4},"shots":{"total":null,"on":null},"goals":{"total":1,"conceded":null,"assists":null,"saves":null},"passes":{"total":null,"key":null,"accuracy":null},"tackles":{"total":null,"blocks":null,"interceptions":null},"duels":{"total":null,"won":null},"dribbles":{"attempts":null,"success":null,"past":null},"fouls":{"drawn":null,"committed":null},"cards":{"yellow":0,"yellowred":0,"red":0},"penalty":{"won":null,"commited":null,"scored":null,"missed":null,"saved":null}}]},{"player":{"id":162024,"name":"K. Ruiz-Atil","firstname":"Kays","lastname":"Ruiz-Atil","age":19,"birth":{"date":"2002-08-26","place":null,"country":"Morocco"},"nationality":"Morocco","height":null,"weight":null,"injured":false,"photo":"https:\/\/media.api-sports.io\/football\/players\/162024.png"},"statistics":[{"team":{"id":85,"name":"Paris Saint Germain","logo":"https:\/\/media.api-sports.io\/football\/teams\/85.png"},"league":{"id":61,"name":"Ligue 1","country":"France","logo":"https:\/\/media.api-sports.io\/football\/leagues\/61.png","flag":"https:\/\/media.api-sports.io\/flags\/fr.svg","season":2021},"games":{"appearences":null,"lineups":null,"minutes":null,"number":null,"position":"Midfielder","rating":null,"captain":false},"substitutes":{"in":null,"out":null,"bench":null},"shots":{"total":null,"on":null},"goals":{"total":null,"conceded":null,"assists":null,"saves":null},"passes":{"total":null,"key":null,"accuracy":null},"tackles":{"total":null,"blocks":null,"interceptions":null},"duels":{"total":null,"won":null},"dribbles":{"attempts":null,"success":null,"past":null},"fouls":{"drawn":null,"committed":null},"cards":{"yellow":null,"yellowred":null,"red":null},"penalty":{"won":null,"commited":null,"scored":null,"missed":null,"saved":null}}]},{"player":{"id":162066,"name":"A. M&apos;Ze","firstname":"Anfane Ahamada","lastname":"M'Ze","age":19,"birth":{"date":"2002-05-07","place":null,"country":"France"},"nationality":"France","height":null,"weight":null,"injured":false,"photo":"https:\/\/media.api-sports.io\/football\/players\/162066.png"},"statistics":[{"team":{"id":85,"name":"Paris Saint Germain","logo":"https:\/\/media.api-sports.io\/football\/teams\/85.png"},"league":{"id":61,"name":"Ligue 1","country":"France","logo":"https:\/\/media.api-sports.io\/football\/leagues\/61.png","flag":"https:\/\/media.api-sports.io\/flags\/fr.svg","season":2021},"games":{"appearences":null,"lineups":null,"minutes":null,"number":null,"position":"Midfielder","rating":null,"captain":false},"substitutes":{"in":null,"out":null,"bench":null},"shots":{"total":null,"on":null},"goals":{"total":null,"conceded":null,"assists":null,"saves":null},"passes":{"total":null,"key":null,"accuracy":null},"tackles":{"total":null,"blocks":null,"interceptions":null},"duels":{"total":null,"won":null},"dribbles":{"attempts":null,"success":null,"past":null},"fouls":{"drawn":null,"committed":null},"cards":{"yellow":null,"yellowred":null,"red":null},"penalty":{"won":null,"commited":null,"scored":null,"missed":null,"saved":null}},{"team":{"id":85,"name":"Paris Saint Germain","logo":"https:\/\/media.api-sports.io\/football\/teams\/85.png"},"league":{"id":null,"name":"Club Friendlies","country":null,"logo":null,"flag":null,"season":"2021"},"games":{"appearences":4,"lineups":1,"minutes":116,"number":null,"position":"Midfielder","rating":null,"captain":false},"substitutes":{"in":3,"out":1,"bench":3},"shots":{"total":null,"on":null},"goals":{"total":0,"conceded":null,"assists":null,"saves":null},"passes":{"total":null,"key":null,"accuracy":null},"tackles":{"total":null,"blocks":null,"interceptions":null},"duels":{"total":null,"won":null},"dribbles":{"attempts":null,"success":null,"past":null},"fouls":{"drawn":null,"committed":null},"cards":{"yellow":0,"yellowred":0,"red":0},"penalty":{"won":null,"commited":null,"scored":null,"missed":null,"saved":null}}]},{"player":{"id":162068,"name":"M. Kapo","firstname":"Maxen","lastname":"Kapo","age":20,"birth":{"date":"2001-01-19","place":"Quincy-sous-S\u00e9nart","country":"France"},"nationality":"France","height":"192 cm","weight":"78 kg","injured":false,"photo":"https:\/\/media.api-sports.io\/football\/players\/162068.png"},"statistics":[{"team":{"id":85,"name":"Paris Saint Germain","logo":"https:\/\/media.api-sports.io\/football\/teams\/85.png"},"league":{"id":null,"name":"Club Friendlies","country":null,"logo":null,"flag":null,"season":"2021"},"games":{"appearences":0,"lineups":0,"minutes":0,"number":null,"position":"Midfielder","rating":null,"captain":false},"substitutes":{"in":0,"out":0,"bench":0},"shots":{"total":null,"on":null},"goals":{"total":0,"conceded":null,"assists":null,"saves":null},"passes":{"total":null,"key":null,"accuracy":null},"tackles":{"total":null,"blocks":null,"interceptions":null},"duels":{"total":null,"won":null},"dribbles":{"attempts":null,"success":null,"past":null},"fouls":{"drawn":null,"committed":null},"cards":{"yellow":0,"yellowred":0,"red":0},"penalty":{"won":null,"commited":null,"scored":null,"missed":null,"saved":null}}]},{"player":{"id":162145,"name":"A. Kamara","firstname":"Abdoulaye","lastname":"Kamara","age":17,"birth":{"date":"2004-11-06","place":null,"country":"Guinea"},"nationality":"Guinea","height":"182 cm","weight":"77 kg","injured":false,"photo":"https:\/\/media.api-sports.io\/football\/players\/162145.png"},"statistics":[{"team":{"id":85,"name":"Paris Saint Germain","logo":"https:\/\/media.api-sports.io\/football\/teams\/85.png"},"league":{"id":null,"name":"Club Friendlies","country":null,"logo":null,"flag":null,"season":"2021"},"games":{"appearences":0,"lineups":0,"minutes":0,"number":null,"position":"Defender","rating":null,"captain":false},"substitutes":{"in":0,"out":0,"bench":0},"shots":{"total":null,"on":null},"goals":{"total":0,"conceded":null,"assists":null,"saves":null},"passes":{"total":null,"key":null,"accuracy":null},"tackles":{"total":null,"blocks":null,"interceptions":null},"duels":{"total":null,"won":null},"dribbles":{"attempts":null,"success":null,"past":null},"fouls":{"drawn":null,"committed":null},"cards":{"yellow":0,"yellowred":0,"red":0},"penalty":{"won":null,"commited":null,"scored":null,"missed":null,"saved":null}}]},{"player":{"id":162146,"name":"K. Nagera","firstname":"Kenny","lastname":"Nagera","age":19,"birth":{"date":"2002-02-21","place":null,"country":"France"},"nationality":"France","height":"177 cm","weight":"70 kg","injured":false,"photo":"https:\/\/media.api-sports.io\/football\/players\/162146.png"},"statistics":[{"team":{"id":85,"name":"Paris Saint Germain","logo":"https:\/\/media.api-sports.io\/football\/teams\/85.png"},"league":{"id":null,"name":"Club Friendlies","country":null,"logo":null,"flag":null,"season":"2021"},"games":{"appearences":3,"lineups":0,"minutes":64,"number":null,"position":"Attacker","rating":null,"captain":false},"substitutes":{"in":3,"out":0,"bench":4},"shots":{"total":null,"on":null},"goals":{"total":1,"conceded":null,"assists":null,"saves":null},"passes":{"total":null,"key":null,"accuracy":null},"tackles":{"total":null,"blocks":null,"interceptions":null},"duels":{"total":null,"won":null},"dribbles":{"attempts":null,"success":null,"past":null},"fouls":{"drawn":null,"committed":null},"cards":{"yellow":0,"yellowred":0,"red":0},"penalty":{"won":null,"commited":null,"scored":null,"missed":null,"saved":null}}]},{"player":{"id":162147,"name":"A. Fressange","firstname":"Alexandre","lastname":"Fressange","age":20,"birth":{"date":"2001-02-02","place":null,"country":"France"},"nationality":"France","height":null,"weight":null,"injured":false,"photo":"https:\/\/media.api-sports.io\/football\/players\/162147.png"},"statistics":[{"team":{"id":85,"name":"Paris Saint Germain","logo":"https:\/\/media.api-sports.io\/football\/teams\/85.png"},"league":{"id":61,"name":"Ligue 1","country":"France","logo":"https:\/\/media.api-sports.io\/football\/leagues\/61.png","flag":"https:\/\/media.api-sports.io\/flags\/fr.svg","season":2021},"games":{"appearences":null,"lineups":null,"minutes":null,"number":null,"position":"Attacker","rating":null,"captain":false},"substitutes":{"in":null,"out":null,"bench":null},"shots":{"total":null,"on":null},"goals":{"total":null,"conceded":null,"assists":null,"saves":null},"passes":{"total":null,"key":null,"accuracy":null},"tackles":{"total":null,"blocks":null,"interceptions":null},"duels":{"total":null,"won":null},"dribbles":{"attempts":null,"success":null,"past":null},"fouls":{"drawn":null,"committed":null},"cards":{"yellow":null,"yellowred":null,"red":null},"penalty":{"won":null,"commited":null,"scored":null,"missed":null,"saved":null}},{"team":{"id":85,"name":"Paris Saint Germain","logo":"https:\/\/media.api-sports.io\/football\/teams\/85.png"},"league":{"id":null,"name":"Club Friendlies","country":null,"logo":null,"flag":null,"season":"2021"},"games":{"appearences":5,"lineups":1,"minutes":55,"number":null,"position":"Attacker","rating":null,"captain":false},"substitutes":{"in":4,"out":1,"bench":4},"shots":{"total":null,"on":null},"goals":{"total":0,"conceded":null,"assists":null,"saves":null},"passes":{"total":null,"key":null,"accuracy":null},"tackles":{"total":null,"blocks":null,"interceptions":null},"duels":{"total":null,"won":null},"dribbles":{"attempts":null,"success":null,"past":null},"fouls":{"drawn":null,"committed":null},"cards":{"yellow":0,"yellowred":0,"red":0},"penalty":{"won":null,"commited":null,"scored":null,"missed":null,"saved":null}}]},{"player":{"id":162528,"name":"D. Franchi","firstname":"Denis","lastname":"Franchi","age":19,"birth":{"date":"2002-01-22","place":null,"country":"Italy"},"nationality":"Italy","height":null,"weight":null,"injured":false,"photo":"https:\/\/media.api-sports.io\/football\/players\/162528.png"},"statistics":[{"team":{"id":85,"name":"Paris Saint Germain","logo":"https:\/\/media.api-sports.io\/football\/teams\/85.png"},"league":{"id":61,"name":"Ligue 1","country":"France","logo":"https:\/\/media.api-sports.io\/football\/leagues\/61.png","flag":"https:\/\/media.api-sports.io\/flags\/fr.svg","season":2021},"games":{"appearences":null,"lineups":null,"minutes":null,"number":null,"position":"Goalkeeper","rating":null,"captain":false},"substitutes":{"in":null,"out":null,"bench":null},"shots":{"total":null,"on":null},"goals":{"total":null,"conceded":null,"assists":null,"saves":null},"passes":{"total":null,"key":null,"accuracy":null},"tackles":{"total":null,"blocks":null,"interceptions":null},"duels":{"total":null,"won":null},"dribbles":{"attempts":null,"success":null,"past":null},"fouls":{"drawn":null,"committed":null},"cards":{"yellow":null,"yellowred":null,"red":null},"penalty":{"won":null,"commited":null,"scored":null,"missed":null,"saved":null}},{"team":{"id":85,"name":"Paris Saint Germain","logo":"https:\/\/media.api-sports.io\/football\/teams\/85.png"},"league":{"id":null,"name":"Club Friendlies","country":null,"logo":null,"flag":null,"season":"2021"},"games":{"appearences":1,"lineups":0,"minutes":44,"number":null,"position":"Goalkeeper","rating":null,"captain":false},"substitutes":{"in":1,"out":0,"bench":4},"shots":{"total":null,"on":null},"goals":{"total":0,"conceded":null,"assists":null,"saves":null},"passes":{"total":null,"key":null,"accuracy":null},"tackles":{"total":null,"blocks":null,"interceptions":null},"duels":{"total":null,"won":null},"dribbles":{"attempts":null,"success":null,"past":null},"fouls":{"drawn":null,"committed":null},"cards":{"yellow":0,"yellowred":0,"red":0},"penalty":{"won":null,"commited":null,"scored":null,"missed":null,"saved":null}}]},{"player":{"id":162532,"name":"Y. Saidani","firstname":"Yanis","lastname":"Saidani","age":20,"birth":{"date":"2001-08-20","place":null,"country":"France"},"nationality":"France","height":null,"weight":null,"injured":false,"photo":"https:\/\/media.api-sports.io\/football\/players\/162532.png"},"statistics":[{"team":{"id":85,"name":"Paris Saint Germain","logo":"https:\/\/media.api-sports.io\/football\/teams\/85.png"},"league":{"id":61,"name":"Ligue 1","country":"France","logo":"https:\/\/media.api-sports.io\/football\/leagues\/61.png","flag":"https:\/\/media.api-sports.io\/flags\/fr.svg","season":2021},"games":{"appearences":null,"lineups":null,"minutes":null,"number":null,"position":"Goalkeeper","rating":null,"captain":false},"substitutes":{"in":null,"out":null,"bench":null},"shots":{"total":null,"on":null},"goals":{"total":null,"conceded":null,"assists":null,"saves":null},"passes":{"total":null,"key":null,"accuracy":null},"tackles":{"total":null,"blocks":null,"interceptions":null},"duels":{"total":null,"won":null},"dribbles":{"attempts":null,"success":null,"past":null},"fouls":{"drawn":null,"committed":null},"cards":{"yellow":null,"yellowred":null,"red":null},"penalty":{"won":null,"commited":null,"scored":null,"missed":null,"saved":null}}]},{"player":{"id":163080,"name":"G. Innocent","firstname":"Garissone","lastname":"Innocent","age":21,"birth":{"date":"2000-04-16","place":"Ivry-sur-Seine","country":"France"},"nationality":"France","height":"192 cm","weight":null,"injured":false,"photo":"https:\/\/media.api-sports.io\/football\/players\/163080.png"},"statistics":[{"team":{"id":85,"name":"Paris Saint Germain","logo":"https:\/\/media.api-sports.io\/football\/teams\/85.png"},"league":{"id":61,"name":"Ligue 1","country":"France","logo":"https:\/\/media.api-sports.io\/football\/leagues\/61.png","flag":"https:\/\/media.api-sports.io\/flags\/fr.svg","season":2021},"games":{"appearences":null,"lineups":null,"minutes":null,"number":null,"position":"Goalkeeper","rating":null,"captain":false},"substitutes":{"in":null,"out":null,"bench":null},"shots":{"total":null,"on":null},"goals":{"total":null,"conceded":null,"assists":null,"saves":null},"passes":{"total":null,"key":null,"accuracy":null},"tackles":{"total":null,"blocks":null,"interceptions":null},"duels":{"total":null,"won":null},"dribbles":{"attempts":null,"success":null,"past":null},"fouls":{"drawn":null,"committed":null},"cards":{"yellow":null,"yellowred":null,"red":null},"penalty":{"won":null,"commited":null,"scored":null,"missed":null,"saved":null}}]},{"player":{"id":288771,"name":"M. Randriamamy","firstname":"Mathyas","lastname":"Randriamamy","age":18,"birth":{"date":"2003-04-23","place":null,"country":"France"},"nationality":"Madagascar","height":"186 cm","weight":null,"injured":false,"photo":"https:\/\/media.api-sports.io\/football\/players\/288771.png"},"statistics":[{"team":{"id":85,"name":"Paris Saint Germain","logo":"https:\/\/media.api-sports.io\/football\/teams\/85.png"},"league":{"id":61,"name":"Ligue 1","country":"France","logo":"https:\/\/media.api-sports.io\/football\/leagues\/61.png","flag":"https:\/\/media.api-sports.io\/flags\/fr.svg","season":2021},"games":{"appearences":null,"lineups":null,"minutes":null,"number":null,"position":"Goalkeeper","rating":null,"captain":false},"substitutes":{"in":null,"out":null,"bench":null},"shots":{"total":null,"on":null},"goals":{"total":null,"conceded":null,"assists":null,"saves":null},"passes":{"total":null,"key":null,"accuracy":null},"tackles":{"total":null,"blocks":null,"interceptions":null},"duels":{"total":null,"won":null},"dribbles":{"attempts":null,"success":null,"past":null},"fouls":{"drawn":null,"committed":null},"cards":{"yellow":null,"yellowred":null,"red":null},"penalty":{"won":null,"commited":null,"scored":null,"missed":null,"saved":null}}]},{"player":{"id":322555,"name":"S. Dauriat","firstname":"Samuel Noireau","lastname":"Dauriat","age":18,"birth":{"date":"2003-01-01","place":null,"country":"France"},"nationality":"France","height":null,"weight":null,"injured":false,"photo":"https:\/\/media.api-sports.io\/football\/players\/322555.png"},"statistics":[{"team":{"id":85,"name":"Paris Saint Germain","logo":"https:\/\/media.api-sports.io\/football\/teams\/85.png"},"league":{"id":61,"name":"Ligue 1","country":"France","logo":"https:\/\/media.api-sports.io\/football\/leagues\/61.png","flag":"https:\/\/media.api-sports.io\/flags\/fr.svg","season":2021},"games":{"appearences":null,"lineups":null,"minutes":null,"number":null,"position":"Attacker","rating":null,"captain":false},"substitutes":{"in":null,"out":null,"bench":null},"shots":{"total":null,"on":null},"goals":{"total":null,"conceded":null,"assists":null,"saves":null},"passes":{"total":null,"key":null,"accuracy":null},"tackles":{"total":null,"blocks":null,"interceptions":null},"duels":{"total":null,"won":null},"dribbles":{"attempts":null,"success":null,"past":null},"fouls":{"drawn":null,"committed":null},"cards":{"yellow":null,"yellowred":null,"red":null},"penalty":{"won":null,"commited":null,"scored":null,"missed":null,"saved":null}},{"team":{"id":85,"name":"Paris Saint Germain","logo":"https:\/\/media.api-sports.io\/football\/teams\/85.png"},"league":{"id":null,"name":"Club Friendlies","country":null,"logo":null,"flag":null,"season":"2021"},"games":{"appearences":2,"lineups":0,"minutes":56,"number":null,"position":"Attacker","rating":null,"captain":false},"substitutes":{"in":2,"out":0,"bench":4},"shots":{"total":null,"on":null},"goals":{"total":0,"conceded":null,"assists":null,"saves":null},"passes":{"total":null,"key":null,"accuracy":null},"tackles":{"total":null,"blocks":null,"interceptions":null},"duels":{"total":null,"won":null},"dribbles":{"attempts":null,"success":null,"past":null},"fouls":{"drawn":null,"committed":null},"cards":{"yellow":0,"yellowred":0,"red":0},"penalty":{"won":null,"commited":null,"scored":null,"missed":null,"saved":null}}]},{"player":{"id":322556,"name":"N. Fernandez","firstname":"Nehemiah","lastname":"Fernandez Veliz","age":17,"birth":{"date":"2004-12-11","place":null,"country":"France"},"nationality":"France","height":null,"weight":null,"injured":false,"photo":"https:\/\/media.api-sports.io\/football\/players\/322556.png"},"statistics":[{"team":{"id":85,"name":"Paris Saint Germain","logo":"https:\/\/media.api-sports.io\/football\/teams\/85.png"},"league":{"id":61,"name":"Ligue 1","country":"France","logo":"https:\/\/media.api-sports.io\/football\/leagues\/61.png","flag":"https:\/\/media.api-sports.io\/flags\/fr.svg","season":2021},"games":{"appearences":null,"lineups":null,"minutes":null,"number":null,"position":"Defender","rating":null,"captain":false},"substitutes":{"in":null,"out":null,"bench":null},"shots":{"total":null,"on":null},"goals":{"total":null,"conceded":null,"assists":null,"saves":null},"passes":{"total":null,"key":null,"accuracy":null},"tackles":{"total":null,"blocks":null,"interceptions":null},"duels":{"total":null,"won":null},"dribbles":{"attempts":null,"success":null,"past":null},"fouls":{"drawn":null,"committed":null},"cards":{"yellow":null,"yellowred":null,"red":null},"penalty":{"won":null,"commited":null,"scored":null,"missed":null,"saved":null}},{"team":{"id":85,"name":"Paris Saint Germain","logo":"https:\/\/media.api-sports.io\/football\/teams\/85.png"},"league":{"id":null,"name":"Club Friendlies","country":null,"logo":null,"flag":null,"season":"2021"},"games":{"appearences":3,"lineups":0,"minutes":45,"number":null,"position":"Defender","rating":null,"captain":false},"substitutes":{"in":3,"out":0,"bench":5},"shots":{"total":null,"on":null},"goals":{"total":0,"conceded":null,"assists":null,"saves":null},"passes":{"total":null,"key":null,"accuracy":null},"tackles":{"total":null,"blocks":null,"interceptions":null},"duels":{"total":null,"won":null},"dribbles":{"attempts":null,"success":null,"past":null},"fouls":{"drawn":null,"committed":null},"cards":{"yellow":0,"yellowred":0,"red":0},"penalty":{"won":null,"commited":null,"scored":null,"missed":null,"saved":null}}]},{"player":{"id":323937,"name":"M. Bodiang","firstname":"Moutanabi","lastname":"Bodiang","age":18,"birth":{"date":"2003-03-14","place":null,"country":"France"},"nationality":"France","height":"172 cm","weight":null,"injured":false,"photo":"https:\/\/media.api-sports.io\/football\/players\/323937.png"},"statistics":[{"team":{"id":85,"name":"Paris Saint Germain","logo":"https:\/\/media.api-sports.io\/football\/teams\/85.png"},"league":{"id":61,"name":"Ligue 1","country":"France","logo":"https:\/\/media.api-sports.io\/football\/leagues\/61.png","flag":"https:\/\/media.api-sports.io\/flags\/fr.svg","season":2021},"games":{"appearences":null,"lineups":null,"minutes":null,"number":null,"position":"Defender","rating":null,"captain":false},"substitutes":{"in":null,"out":null,"bench":null},"shots":{"total":null,"on":null},"goals":{"total":null,"conceded":null,"assists":null,"saves":null},"passes":{"total":null,"key":null,"accuracy":null},"tackles":{"total":null,"blocks":null,"interceptions":null},"duels":{"total":null,"won":null},"dribbles":{"attempts":null,"success":null,"past":null},"fouls":{"drawn":null,"committed":null},"cards":{"yellow":null,"yellowred":null,"red":null},"penalty":{"won":null,"commited":null,"scored":null,"missed":null,"saved":null}},{"team":{"id":85,"name":"Paris Saint Germain","logo":"https:\/\/media.api-sports.io\/football\/teams\/85.png"},"league":{"id":null,"name":"Club Friendlies","country":null,"logo":null,"flag":null,"season":"2021"},"games":{"appearences":0,"lineups":0,"minutes":0,"number":null,"position":"Defender","rating":null,"captain":false},"substitutes":{"in":0,"out":0,"bench":1},"shots":{"total":null,"on":null},"goals":{"total":0,"conceded":null,"assists":null,"saves":null},"passes":{"total":null,"key":null,"accuracy":null},"tackles":{"total":null,"blocks":null,"interceptions":null},"duels":{"total":null,"won":null},"dribbles":{"attempts":null,"success":null,"past":null},"fouls":{"drawn":null,"committed":null},"cards":{"yellow":0,"yellowred":0,"red":0},"penalty":{"won":null,"commited":null,"scored":null,"missed":null,"saved":null}}]}]}