{"get":"players","parameters":{"team":"571","season":"2021"},"errors":[],"results":20,"paging":{"current":1,"total":3},"response":[{"player":{"id":656,"name":"O. Solet","firstname":"Oumar Mickael","lastname":"Solet Bomawoko","age":21,"birth":{"date":"2000-02-07","place":null,"country":"France"},"nationality":"France","height":"192 cm","weight":"81 kg","injured":false,"photo":"https:\/\/media.api-sports.io\/football\/players\/656.png"},"statistics":[{"team":{"id":571,"name":"Red Bull Salzburg","logo":"https:\/\/media.api-sports.io\/football\/teams\/571.png"},"league":{"id":218,"name":"Tipp3 Bundesliga","country":"Austria","logo":"https:\/\/media.api-sports.io\/football\/leagues\/218.png","flag":"https:\/\/media.api-sports.io\/flags\/at.svg","season":2021},"games":{"appearences":8,"lineups":8,"minutes":607,"number":null,"position":"Defender","rating":"7.125000","captain":false},"substitutes":{"in":0,"out":2,"bench":1},"shots":{"total":4,"on":null},"goals":{"total":0,"conceded":0,"assists":null,"saves":null},"passes":{"total":474,"key":2,"accuracy":54},"tackles":{"total":6,"blocks":6,"interceptions":18},"duels":{"total":51,"won":25},"dribbles":{"attempts":7,"success":7,"past":null},"fouls":{"drawn":5,"committed":11},"cards":{"yellow":0,"yellowred":0,"red":0},"penalty":{"won":null,"commited":null,"scored":0,"missed":0,"saved":null}},{"team":{"id":571,"name":"Red Bull Salzburg","logo":"https:\/\/media.api-sports.io\/football\/teams\/571.png"},"league":{"id":220,"name":"Cup","country":"Austria","logo":"https:\/\/media.api-sports.io\/football\/leagues\/220.png","flag":"https:\/\/media.api-sports.io\/flags\/at.svg","season":2021},"games":{"appearences":1,"lineups":1,"minutes":90,"number":null,"position":"Defender","rating":null,"captain":false},"substitutes":{"in":0,"out":0,"bench":0},"shots":{"total":null,"on":null},"goals":{"total":0,"conceded":null,"assists":null,"saves":null},"passes":{"total":null,"key":null,"accuracy":null},"tackles":{"total":null,"blocks":null,"interceptions":null},"duels":{"total":null,"won":null},"dribbles":{"attempts":null,"success":null,"past":null},"fouls":{"drawn":null,"committed":null},"cards":{"yellow":0,"yellowred":0,"red":0},"penalty":{"won":null,"commited":null,"scored":null,"missed":null,"saved":null}},{"team":{"id":571,"name":"Red Bull Salzburg","logo":"https:\/\/media.api-sports.io\/football\/teams\/571.png"},"league":{"id":2,"name":"UEFA Champions League","country":"World","logo":"https:\/\/media.api-sports.io\/football\/leagues\/2.png","flag":null,"season":2021},"games":{"appearences":4,"lineups":3,"minutes":283,"number":null,"position":"Defender","rating":"6.825000","captain":false},"substitutes":{"in":1,"out":0,"bench":1},"shots":{"total":2,"on":2},"goals":{"total":0,"conceded":0,"assists":1,"saves":null},"passes":{"total":219,"key":1,"accuracy":49},"tackles":{"total":2,"blocks":1,"interceptions":5},"duels":{"total":19,"won":6},"dribbles":{"attempts":2,"success":1,"past":null},"fouls":{"drawn":1,"committed":4},"cards":{"yellow":1,"yellowred":0,"red":0},"penalty":{"won":null,"commited":null,"scored":0,"missed":0,"saved":null}},{"team":{"id":571,"name":"Red Bull Salzburg","logo":"https:\/\/media.api-sports.io\/football\/teams\/571.png"},"league":{"id":null,"name":"Club Friendlies","country":null,"logo":null,"flag":null,"season":"2021"},"games":{"appearences":2,"lineups":0,"minutes":88,"number":null,"position":"Defender","rating":null,"captain":false},"substitutes":{"in":2,"out":0,"bench":2},"shots":{"total":null,"on":null},"goals":{"total":0,"conceded":null,"assists":null,"saves":null},"passes":{"total":null,"key":null,"accuracy":null},"tackles":{"total":null,"blocks":null,"interceptions":null},"duels":{"total":null,"won":null},"dribbles":{"attempts":null,"success":null,"past":null},"fouls":{"drawn":null,"committed":null},"cards":{"yellow":0,"yellowred":0,"red":0},"penalty":{"won":null,"commited":null,"scored":null,"missed":null,"saved":null}}]},{"player":{"id":1080,"name":"A. Walke","firstname":"Alexander","lastname":"Walke","age":38,"birth":{"date":"1983-06-06","place":"Oranienburg","country":"Germany"},"nationality":"Germany","height":"189 cm","weight":"88 kg","injured":false,"photo":"https:\/\/media.api-sports.io\/football\/players\/1080.png"},"statistics":[{"team":{"id":571,"name":"Red Bull Salzburg","logo":"https:\/\/media.api-sports.io\/football\/teams\/571.png"},"league":{"id":218,"name":"Tipp3 Bundesliga","country":"Austria","logo":"https:\/\/media.api-sports.io\/football\/leagues\/218.png","flag":"https:\/\/media.api-sports.io\/flags\/at.svg","season":2021},"games":{"appearences":0,"lineups":0,"minutes":0,"number":null,"position":"Goalkeeper","rating":null,"captain":false},"substitutes":{"in":0,"out":0,"bench":0},"shots":{"total":null,"on":null},"goals":{"total":0,"conceded":null,"assists":null,"saves":null},"passes":{"total":null,"key":null,"accuracy":null},"tackles":{"total":null,"blocks":null,"interceptions":null},"duels":{"total":null,"won":null},"dribbles":{"attempts":null,"success":null,"past":null},"fouls":{"drawn":null,"committed":null},"cards":{"yellow":0,"yellowred":0,"red":0},"penalty":{"won":null,"commited":null,"scored":null,"missed":null,"saved":null}},{"team":{"id":571,"name":"Red Bull Salzburg","logo":"https:\/\/media.api-sports.io\/football\/teams\/571.png"},"league":{"id":220,"name":"Cup","country":"Austria","logo":"https:\/\/media.api-sports.io\/football\/leagues\/220.png","flag":"https:\/\/media.api-sports.io\/flags\/at.svg","season":2021},"games":{"appearences":0,"lineups":0,"minutes":0,"number":null,"position":"Goalkeeper","rating":null,"captain":false},"substitutes":{"in":0,"out":0,"bench":0},"shots":{"total":null,"on":null},"goals":{"total":0,"conceded":null,"assists":null,"saves":null},"passes":{"total":null,"key":null,"accuracy":null},"tackles":{"total":null,"blocks":null,"interceptions":null},"duels":{"total":null,"won":null},"dribbles":{"attempts":null,"success":null,"past":null},"fouls":{"drawn":null,"committed":null},"cards":{"yellow":0,"yellowred":0,"red":0},"penalty":{"won":null,"commited":null,"scored":null,"missed":null,"saved":null}},{"team":{"id":571,"name":"Red Bull Salzburg","logo":"https:\/\/media.api-sports.io\/football\/teams\/571.png"},"league":{"id":2,"name":"UEFA Champions League","country":"World","logo":"https:\/\/media.api-sports.io\/football\/leagues\/2.png","flag":null,"season":2021},"games":{"appearences":0,"lineups":0,"minutes":0,"number":null,"position":"Goalkeeper","rating":null,"captain":false},"substitutes":{"in":0,"out":0,"bench":6},"shots":{"total":null,"on":null},"goals":{"total":0,"conceded":0,"assists":null,"saves":null},"passes":{"total":null,"key":null,"accuracy":null},"tackles":{"total":null,"blocks":null,"interceptions":null},"duels":{"total":null,"won":null},"dribbles":{"attempts":null,"success":null,"past":null},"fouls":{"drawn":null,"committed":null},"cards":{"yellow":0,"yellowred":0,"red":0},"penalty":{"won":null,"commited":null,"scored":0,"missed":0,"saved":0}},{"team":{"id":571,"name":"Red Bull Salzburg","logo":"https:\/\/media.api-sports.io\/football\/teams\/571.png"},"league":{"id":null,"name":"Club Friendlies","country":null,"logo":null,"flag":null,"season":"2021"},"games":{"appearences":0,"lineups":0,"minutes":0,"number":null,"position":"Goalkeeper","rating":null,"captain":false},"substitutes":{"in":0,"out":0,"bench":0},"shots":{"total":null,"on":null},"goals":{"total":0,"conceded":null,"assists":null,"saves":null},"passes":{"total":null,"key":null,"accuracy":null},"tackles":{"total":null,"blocks":null,"interceptions":null},"duels":{"total":null,"won":null},"dribbles":{"attempts":null,"success":null,"past":null},"fouls":{"drawn":null,"committed":null},"cards":{"yellow":0,"yellowred":0,"red":0},"penalty":{"won":null,"commited":null,"scored":null,"missed":null,"saved":null}}]},{"player":{"id":1083,"name":"J. Ongu\u00e9n\u00e9","firstname":"J\u00e9r\u00f4me Junior","lastname":"Ongu\u00e9n\u00e9","age":24,"birth":{"date":"1997-12-22","place":"Mbalayo","country":"Cameroon"},"nationality":"Cameroon","height":"186 cm","weight":"78 kg","injured":false,"photo":"https:\/\/media.api-sports.io\/football\/players\/1083.png"},"statistics":[{"team":{"id":571,"name":"Red Bull Salzburg","logo":"https:\/\/media.api-sports.io\/football\/teams\/571.png"},"league":{"id":218,"name":"Tipp3 Bundesliga","country":"Austria","logo":"https:\/\/media.api-sports.io\/football\/leagues\/218.png","flag":"https:\/\/media.api-sports.io\/flags\/at.svg","season":2021},"games":{"appearences":7,"lineups":5,"minutes":563,"number":null,"position":"Defender","rating":"7.114285","captain":false},"substitutes":{"in":2,"out":0,"bench":3},"shots":{"total":4,"on":1},"goals":{"total":1,"conceded":0,"assists":null,"saves":null},"passes":{"total":435,"key":null,"accuracy":51},"tackles":{"total":12,"blocks":4,"interceptions":11},"duels":{"total":66,"won":44},"dribbles":{"attempts":1,"success":1,"past":null},"fouls":{"drawn":2,"committed":3},"cards":{"yellow":2,"yellowred":0,"red":0},"penalty":{"won":null,"commited":null,"scored":0,"missed":0,"saved":null}},{"team":{"id":571,"name":"Red Bull Salzburg","logo":"https:\/\/media.api-sports.io\/football\/teams\/571.png"},"league":{"id":220,"name":"Cup","country":"Austria","logo":"https:\/\/media.api-sports.io\/football\/leagues\/220.png","flag":"https:\/\/media.api-sports.io\/flags\/at.svg","season":2021},"games":{"appearences":2,"lineups":2,"minutes":180,"number":null,"position":"Defender","rating":null,"captain":false},"substitutes":{"in":0,"out":0,"bench":1},"shots":{"total":null,"on":null},"goals":{"total":0,"conceded":null,"assists":null,"saves":null},"passes":{"total":null,"key":null,"accuracy":null},"tackles":{"total":null,"blocks":null,"interceptions":null},"duels":{"total":null,"won":null},"dribbles":{"attempts":null,"success":null,"past":null},"fouls":{"drawn":null,"committed":null},"cards":{"yellow":0,"yellowred":0,"red":0},"penalty":{"won":null,"commited":null,"scored":null,"missed":null,"saved":null}},{"team":{"id":571,"name":"Red Bull Salzburg","logo":"https:\/\/media.api-sports.io\/football\/teams\/571.png"},"league":{"id":2,"name":"UEFA Champions League","country":"World","logo":"https:\/\/media.api-sports.io\/football\/leagues\/2.png","flag":null,"season":2021},"games":{"appearences":3,"lineups":3,"minutes":257,"number":null,"position":"Defender","rating":"6.766666","captain":false},"substitutes":{"in":0,"out":1,"bench":1},"shots":{"total":null,"on":null},"goals":{"total":0,"conceded":0,"assists":null,"saves":null},"passes":{"total":177,"key":null,"accuracy":50},"tackles":{"total":1,"blocks":1,"interceptions":10},"duels":{"total":24,"won":12},"dribbles":{"attempts":1,"success":1,"past":null},"fouls":{"drawn":2,"committed":4},"cards":{"yellow":0,"yellowred":0,"red":0},"penalty":{"won":null,"commited":null,"scored":0,"missed":0,"saved":null}},{"team":{"id":571,"name":"Red Bull Salzburg","logo":"https:\/\/media.api-sports.io\/football\/teams\/571.png"},"league":{"id":null,"name":"Club Friendlies","country":null,"logo":null,"flag":null,"season":"2021"},"games":{"appearences":2,"lineups":1,"minutes":88,"number":null,"position":"Defender","rating":null,"captain":false},"substitutes":{"in":1,"out":2,"bench":1},"shots":{"total":null,"on":null},"goals":{"total":0,"conceded":null,"assists":null,"saves":null},"passes":{"total":null,"key":null,"accuracy":null},"tackles":{"total":null,"blocks":null,"interceptions":null},"duels":{"total":null,"won":null},"dribbles":{"attempts":null,"success":null,"past":null},"fouls":{"drawn":null,"committed":null},"cards":{"yellow":0,"yellowred":0,"red":0},"penalty":{"won":null,"commited":null,"scored":null,"missed":null,"saved":null}},{"team":{"id":571,"name":"Red Bull Salzburg","logo":"https:\/\/media.api-sports.io\/football\/teams\/571.png"},"league":{"id":null,"name":"Club Friendlies","country":null,"logo":null,"flag":null,"season":"2021"},"games":{"appearences":0,"lineups":0,"minutes":0,"number":null,"position":"Defender","rating":null,"captain":false},"substitutes":{"in":0,"out":0,"bench":0},"shots":{"total":null,"on":null},"goals":{"total":0,"conceded":null,"assists":null,"saves":null},"passes":{"total":null,"key":null,"accuracy":null},"tackles":{"total":null,"blocks":null,"interceptions":null},"duels":{"total":null,"won":null},"dribbles":{"attempts":null,"success":null,"past":null},"fouls":{"drawn":null,"committed":null},"cards":{"yellow":0,"yellowred":0,"red":0},"penalty":{"won":null,"commited":null,"scored":null,"missed":null,"saved":null}}]},{"player":{"id":1086,"name":"D. Todorovi\u0107","firstname":"Darko","lastname":"Todorovi\u0107","age":24,"birth":{"date":"1997-05-05","place":"Bijeljina","country":"Bosnia and Herzegovina"},"nationality":"Bosnia and Herzegovina","height":"174 cm","weight":"70 kg","injured":false,"photo":"https:\/\/media.api-sports.io\/football\/players\/1086.png"},"statistics":[{"team":{"id":571,"name":"Red Bull Salzburg","logo":"https:\/\/media.api-sports.io\/football\/teams\/571.png"},"league":{"id":null,"name":"Club Friendlies","country":null,"logo":null,"flag":null,"season":"2021"},"games":{"appearences":0,"lineups":0,"minutes":0,"number":null,"position":"Defender","rating":null,"captain":false},"substitutes":{"in":0,"out":0,"bench":0},"shots":{"total":null,"on":null},"goals":{"total":0,"conceded":null,"assists":null,"saves":null},"passes":{"total":null,"key":null,"accuracy":null},"tackles":{"total":null,"blocks":null,"interceptions":null},"duels":{"total":null,"won":null},"dribbles":{"attempts":null,"success":null,"past":null},"fouls":{"drawn":null,"committed":null},"cards":{"yellow":0,"yellowred":0,"red":0},"penalty":{"won":null,"commited":null,"scored":null,"missed":null,"saved":null}}]},{"player":{"id":1088,"name":"A. Vall\u00e7i","firstname":"Albert","lastname":"Vall\u00e7i","age":26,"birth":{"date":"1995-07-02","place":"Voitsberg","country":"Austria"},"nationality":"Austria","height":"191 cm","weight":null,"injured":false,"photo":"https:\/\/media.api-sports.io\/football\/players\/1088.png"},"statistics":[{"team":{"id":571,"name":"Red Bull Salzburg","logo":"https:\/\/media.api-sports.io\/football\/teams\/571.png"},"league":{"id":218,"name":"Tipp3 Bundesliga","country":"Austria","logo":"https:\/\/media.api-sports.io\/football\/leagues\/218.png","flag":"https:\/\/media.api-sports.io\/flags\/at.svg","season":2021},"games":{"appearences":0,"lineups":0,"minutes":0,"number":null,"position":"Defender","rating":null,"captain":false},"substitutes":{"in":0,"out":0,"bench":0},"shots":{"total":null,"on":null},"goals":{"total":0,"conceded":null,"assists":null,"saves":null},"passes":{"total":null,"key":null,"accuracy":null},"tackles":{"total":null,"blocks":null,"interceptions":null},"duels":{"total":null,"won":null},"dribbles":{"attempts":null,"success":null,"past":null},"fouls":{"drawn":null,"committed":null},"cards":{"yellow":0,"yellowred":0,"red":0},"penalty":{"won":null,"commited":null,"scored":null,"missed":null,"saved":null}},{"team":{"id":571,"name":"Red Bull Salzburg","logo":"https:\/\/media.api-sports.io\/football\/teams\/571.png"},"league":{"id":220,"name":"Cup","country":"Austria","logo":"https:\/\/media.api-sports.io\/football\/leagues\/220.png","flag":"https:\/\/media.api-sports.io\/flags\/at.svg","season":2021},"games":{"appearences":0,"lineups":0,"minutes":0,"number":null,"position":"Defender","rating":null,"captain":false},"substitutes":{"in":0,"out":0,"bench":0},"shots":{"total":null,"on":null},"goals":{"total":0,"conceded":null,"assists":null,"saves":null},"passes":{"total":null,"key":null,"accuracy":null},"tackles":{"total":null,"blocks":null,"interceptions":null},"duels":{"total":null,"won":null},"dribbles":{"attempts":null,"success":null,"past":null},"fouls":{"drawn":null,"committed":null},"cards":{"yellow":0,"yellowred":0,"red":0},"penalty":{"won":null,"commited":null,"scored":null,"missed":null,"saved":null}},{"team":{"id":571,"name":"Red Bull Salzburg","logo":"https:\/\/media.api-sports.io\/football\/teams\/571.png"},"league":{"id":2,"name":"UEFA Champions League","country":"World","logo":"https:\/\/media.api-sports.io\/football\/leagues\/2.png","flag":null,"season":2021},"games":{"appearences":0,"lineups":0,"minutes":0,"number":null,"position":"Defender","rating":null,"captain":false},"substitutes":{"in":0,"out":0,"bench":0},"shots":{"total":null,"on":null},"goals":{"total":0,"conceded":null,"assists":null,"saves":null},"passes":{"total":null,"key":null,"accuracy":null},"tackles":{"total":null,"blocks":null,"interceptions":null},"duels":{"total":null,"won":null},"dribbles":{"attempts":null,"success":null,"past":null},"fouls":{"drawn":null,"committed":null},"cards":{"yellow":0,"yellowred":0,"red":0},"penalty":{"won":null,"commited":null,"scored":null,"missed":null,"saved":null}},{"team":{"id":571,"name":"Red Bull Salzburg","logo":"https:\/\/media.api-sports.io\/football\/teams\/571.png"},"league":{"id":null,"name":"Club Friendlies","country":null,"logo":null,"flag":null,"season":"2021"},"games":{"appearences":0,"lineups":0,"minutes":0,"number":null,"position":"Defender","rating":null,"captain":false},"substitutes":{"in":0,"out":0,"bench":0},"shots":{"total":null,"on":null},"goals":{"total":0,"conceded":null,"assists":null,"saves":null},"passes":{"total":null,"key":null,"accuracy":null},"tackles":{"total":null,"blocks":null,"interceptions":null},"duels":{"total":null,"won":null},"dribbles":{"attempts":null,"success":null,"past":null},"fouls":{"drawn":null,"committed":null},"cards":{"yellow":0,"yellowred":0,"red":0},"penalty":{"won":null,"commited":null,"scored":null,"missed":null,"saved":null}}]},{"player":{"id":2048,"name":"M. W\u00f6ber","firstname":"Maximilian","lastname":"W\u00f6ber","age":23,"birth":{"date":"1998-02-04","place":"Wien","country":"Austria"},"nationality":"Austria","height":"188 cm","weight":"82 kg","injured":false,"photo":"https:\/\/media.api-sports.io\/football\/players\/2048.png"},"statistics":[{"team":{"id":571,"name":"Red Bull Salzburg","logo":"https:\/\/media.api-sports.io\/football\/teams\/571.png"},"league":{"id":218,"name":"Tipp3 Bundesliga","country":"Austria","logo":"https:\/\/media.api-sports.io\/football\/leagues\/218.png","flag":"https:\/\/media.api-sports.io\/flags\/at.svg","season":2021},"games":{"appearences":10,"lineups":9,"minutes":787,"number":null,"position":"Defender","rating":"7.330000","captain":false},"substitutes":{"in":1,"out":2,"bench":2},"shots":{"total":4,"on":2},"goals":{"total":1,"conceded":0,"assists":1,"saves":null},"passes":{"total":611,"key":4,"accuracy":47},"tackles":{"total":16,"blocks":6,"interceptions":17},"duels":{"total":113,"won":77},"dribbles":{"attempts":null,"success":null,"past":null},"fouls":{"drawn":3,"committed":15},"cards":{"yellow":4,"yellowred":0,"red":0},"penalty":{"won":null,"commited":null,"scored":0,"missed":0,"saved":null}},{"team":{"id":571,"name":"Red Bull Salzburg","logo":"https:\/\/media.api-sports.io\/football\/teams\/571.png"},"league":{"id":220,"name":"Cup","country":"Austria","logo":"https:\/\/media.api-sports.io\/football\/leagues\/220.png","flag":"https:\/\/media.api-sports.io\/flags\/at.svg","season":2021},"games":{"appearences":2,"lineups":2,"minutes":180,"number":null,"position":"Defender","rating":null,"captain":false},"substitutes":{"in":0,"out":0,"bench":0},"shots":{"total":null,"on":null},"goals":{"total":0,"conceded":null,"assists":null,"saves":null},"passes":{"total":null,"key":null,"accuracy":null},"tackles":{"total":null,"blocks":null,"interceptions":null},"duels":{"total":null,"won":null},"dribbles":{"attempts":null,"success":null,"past":null},"fouls":{"drawn":null,"committed":null},"cards":{"yellow":0,"yellowred":0,"red":0},"penalty":{"won":null,"commited":null,"scored":null,"missed":null,"saved":null}},{"team":{"id":571,"name":"Red Bull Salzburg","logo":"https:\/\/media.api-sports.io\/football\/teams\/571.png"},"league":{"id":2,"name":"UEFA Champions League","country":"World","logo":"https:\/\/media.api-sports.io\/football\/leagues\/2.png","flag":null,"season":2021},"games":{"appearences":6,"lineups":6,"minutes":483,"number":null,"position":"Defender","rating":"6.816666","captain":false},"substitutes":{"in":0,"out":2,"bench":0},"shots":{"total":3,"on":1},"goals":{"total":1,"conceded":0,"assists":null,"saves":null},"passes":{"total":373,"key":2,"accuracy":47},"tackles":{"total":6,"blocks":2,"interceptions":9},"duels":{"total":52,"won":27},"dribbles":{"attempts":1,"success":1,"past":null},"fouls":{"drawn":3,"committed":3},"cards":{"yellow":0,"yellowred":0,"red":0},"penalty":{"won":null,"commited":null,"scored":0,"missed":0,"saved":null}},{"team":{"id":571,"name":"Red Bull Salzburg","logo":"https:\/\/media.api-sports.io\/football\/teams\/571.png"},"league":{"id":null,"name":"Club Friendlies","country":null,"logo":null,"flag":null,"season":"2021"},"games":{"appearences":2,"lineups":2,"minutes":92,"number":null,"position":"Defender","rating":null,"captain":false},"substitutes":{"in":0,"out":2,"bench":0},"shots":{"total":null,"on":null},"goals":{"total":0,"conceded":null,"assists":null,"saves":null},"passes":{"total":null,"key":null,"accuracy":null},"tackles":{"total":null,"blocks":null,"interceptions":null},"duels":{"total":null,"won":null},"dribbles":{"attempts":null,"success":null,"past":null},"fouls":{"drawn":null,"committed":null},"cards":{"yellow":0,"yellowred":0,"red":0},"penalty":{"won":null,"commited":null,"scored":null,"missed":null,"saved":null}}]},{"player":{"id":5973,"name":"N. Capaldo","firstname":"Nicol\u00e1s","lastname":"Capaldo Toboas","age":23,"birth":{"date":"1998-09-14","place":"Santa Rosa","country":"Argentina"},"nationality":"Argentina","height":"177 cm","weight":"73 kg","injured":false,"photo":"https:\/\/media.api-sports.io\/football\/players\/5973.png"},"statistics":[{"team":{"id":571,"name":"Red Bull Salzburg","logo":"https:\/\/media.api-sports.io\/football\/teams\/571.png"},"league":{"id":218,"name":"Tipp3 Bundesliga","country":"Austria","logo":"https:\/\/media.api-sports.io\/football\/leagues\/218.png","flag":"https:\/\/media.api-sports.io\/flags\/at.svg","season":2021},"games":{"appearences":14,"lineups":8,"minutes":691,"number":null,"position":"Midfielder","rating":"6.878571","captain":false},"substitutes":{"in":6,"out":6,"bench":6},"shots":{"total":12,"on":7},"goals":{"total":2,"conceded":0,"assists":1,"saves":null},"passes":{"total":311,"key":15,"accuracy":17},"tackles":{"total":14,"blocks":1,"interceptions":5},"duels":{"total":96,"won":42},"dribbles":{"attempts":8,"success":6,"past":null},"fouls":{"drawn":12,"committed":17},"cards":{"yellow":5,"yellowred":0,"red":0},"penalty":{"won":null,"commited":null,"scored":0,"missed":0,"saved":null}},{"team":{"id":571,"name":"Red Bull Salzburg","logo":"https:\/\/media.api-sports.io\/football\/teams\/571.png"},"league":{"id":220,"name":"Cup","country":"Austria","logo":"https:\/\/media.api-sports.io\/football\/leagues\/220.png","flag":"https:\/\/media.api-sports.io\/flags\/at.svg","season":2021},"games":{"appearences":3,"lineups":3,"minutes":248,"number":null,"position":"Midfielder","rating":null,"captain":false},"substitutes":{"in":0,"out":1,"bench":0},"shots":{"total":null,"on":null},"goals":{"total":1,"conceded":null,"assists":null,"saves":null},"passes":{"total":null,"key":null,"accuracy":null},"tackles":{"total":null,"blocks":null,"interceptions":null},"duels":{"total":null,"won":null},"dribbles":{"attempts":null,"success":null,"past":null},"fouls":{"drawn":null,"committed":null},"cards":{"yellow":0,"yellowred":0,"red":0},"penalty":{"won":null,"commited":null,"scored":null,"missed":null,"saved":null}},{"team":{"id":571,"name":"Red Bull Salzburg","logo":"https:\/\/media.api-sports.io\/football\/teams\/571.png"},"league":{"id":2,"name":"UEFA Champions League","country":"World","logo":"https:\/\/media.api-sports.io\/football\/leagues\/2.png","flag":null,"season":2021},"games":{"appearences":4,"lineups":1,"minutes":99,"number":null,"position":"Midfielder","rating":"6.550000","captain":false},"substitutes":{"in":3,"out":1,"bench":4},"shots":{"total":1,"on":null},"goals":{"total":0,"conceded":0,"assists":null,"saves":null},"passes":{"total":58,"key":null,"accuracy":11},"tackles":{"total":1,"blocks":1,"interceptions":5},"duels":{"total":16,"won":6},"dribbles":{"attempts":2,"success":1,"past":null},"fouls":{"drawn":3,"committed":3},"cards":{"yellow":3,"yellowred":0,"red":0},"penalty":{"won":null,"commited":null,"scored":0,"missed":0,"saved":null}},{"team":{"id":571,"name":"Red Bull Salzburg","logo":"https:\/\/media.api-sports.io\/football\/teams\/571.png"},"league":{"id":null,"name":"Club Friendlies","country":null,"logo":null,"flag":null,"season":"2021"},"games":{"appearences":2,"lineups":1,"minutes":90,"number":null,"position":"Midfielder","rating":null,"captain":false},"substitutes":{"in":1,"out":1,"bench":1},"shots":{"total":null,"on":null},"goals":{"total":0,"conceded":null,"assists":null,"saves":null},"passes":{"total":null,"key":null,"accuracy":null},"tackles":{"total":null,"blocks":null,"interceptions":null},"duels":{"total":null,"won":null},"dribbles":{"attempts":null,"success":null,"past":null},"fouls":{"drawn":null,"committed":null},"cards":{"yellow":0,"yellowred":0,"red":0},"penalty":{"won":null,"commited":null,"scored":null,"missed":null,"saved":null}}]},{"player":{"id":7315,"name":"A. Stejskal","firstname":"Adam","lastname":"Stejskal","age":19,"birth":{"date":"2002-08-23","place":"Brno","country":"Czech Republic"},"nationality":"Czech Republic","height":"189 cm","weight":"67 kg","injured":false,"photo":"https:\/\/media.api-sports.io\/football\/players\/7315.png"},"statistics":[{"team":{"id":571,"name":"Red Bull Salzburg","logo":"https:\/\/media.api-sports.io\/football\/teams\/571.png"},"league":{"id":218,"name":"Tipp3 Bundesliga","country":"Austria","logo":"https:\/\/media.api-sports.io\/football\/leagues\/218.png","flag":"https:\/\/media.api-sports.io\/flags\/at.svg","season":2021},"games":{"appearences":0,"lineups":0,"minutes":0,"number":null,"position":"Goalkeeper","rating":null,"captain":false},"substitutes":{"in":0,"out":0,"bench":0},"shots":{"total":null,"on":null},"goals":{"total":0,"conceded":null,"assists":null,"saves":null},"passes":{"total":null,"key":null,"accuracy":null},"tackles":{"total":null,"blocks":null,"interceptions":null},"duels":{"total":null,"won":null},"dribbles":{"attempts":null,"success":null,"past":null},"fouls":{"drawn":null,"committed":null},"cards":{"yellow":0,"yellowred":0,"red":0},"penalty":{"won":null,"commited":null,"scored":null,"missed":null,"saved":null}},{"team":{"id":571,"name":"Red Bull Salzburg","logo":"https:\/\/media.api-sports.io\/football\/teams\/571.png"},"league":{"id":null,"name":"Club Friendlies","country":null,"logo":null,"flag":null,"season":"2021"},"games":{"appearences":0,"lineups":0,"minutes":0,"number":null,"position":"Goalkeeper","rating":null,"captain":false},"substitutes":{"in":0,"out":0,"bench":0},"shots":{"total":null,"on":null},"goals":{"total":0,"conceded":null,"assists":null,"saves":null},"passes":{"total":null,"key":null,"accuracy":null},"tackles":{"total":null,"blocks":null,"interceptions":null},"duels":{"total":null,"won":null},"dribbles":{"attempts":null,"success":null,"past":null},"fouls":{"drawn":null,"committed":null},"cards":{"yellow":0,"yellowred":0,"red":0},"penalty":{"won":null,"commited":null,"scored":null,"missed":null,"saved":null}}]},{"player":{"id":7318,"name":"A. Dedi\u0107","firstname":"Amar","lastname":"Dedi\u0107","age":19,"birth":{"date":"2002-08-18","place":"Zell am See","country":"Bosnia and Herzegovina"},"nationality":"Bosnia and Herzegovina","height":"180 cm","weight":"70 kg","injured":false,"photo":"https:\/\/media.api-sports.io\/football\/players\/7318.png"},"statistics":[{"team":{"id":571,"name":"Red Bull Salzburg","logo":"https:\/\/media.api-sports.io\/football\/teams\/571.png"},"league":{"id":null,"name":"Club Friendlies","country":null,"logo":null,"flag":null,"season":"2021"},"games":{"appearences":0,"lineups":0,"minutes":0,"number":null,"position":"Defender","rating":null,"captain":false},"substitutes":{"in":0,"out":0,"bench":0},"shots":{"total":null,"on":null},"goals":{"total":0,"conceded":null,"assists":null,"saves":null},"passes":{"total":null,"key":null,"accuracy":null},"tackles":{"total":null,"blocks":null,"interceptions":null},"duels":{"total":null,"won":null},"dribbles":{"attempts":null,"success":null,"past":null},"fouls":{"drawn":null,"committed":null},"cards":{"yellow":0,"yellowred":0,"red":0},"penalty":{"won":null,"commited":null,"scored":null,"missed":null,"saved":null}}]},{"player":{"id":7341,"name":"K. Ludewig","firstname":"Kilian","lastname":"Ludewig","age":21,"birth":{"date":"2000-03-05","place":"Hamburg","country":"Germany"},"nationality":"Germany","height":"175 cm","weight":"66 kg","injured":false,"photo":"https:\/\/media.api-sports.io\/football\/players\/7341.png"},"statistics":[{"team":{"id":571,"name":"Red Bull Salzburg","logo":"https:\/\/media.api-sports.io\/football\/teams\/571.png"},"league":{"id":218,"name":"Tipp3 Bundesliga","country":"Austria","logo":"https:\/\/media.api-sports.io\/football\/leagues\/218.png","flag":"https:\/\/media.api-sports.io\/flags\/at.svg","season":2021},"games":{"appearences":1,"lineups":0,"minutes":62,"number":null,"position":"Defender","rating":"6.300000","captain":false},"substitutes":{"in":1,"out":0,"bench":2},"shots":{"total":2,"on":1},"goals":{"total":0,"conceded":0,"assists":null,"saves":null},"passes":{"total":28,"key":null,"accuracy":18},"tackles":{"total":1,"blocks":null,"interceptions":null},"duels":{"total":7,"won":4},"dribbles":{"attempts":1,"success":1,"past":null},"fouls":{"drawn":null,"committed":null},"cards":{"yellow":0,"yellowred":0,"red":0},"penalty":{"won":null,"commited":null,"scored":0,"missed":0,"saved":null}},{"team":{"id":571,"name":"Red Bull Salzburg","logo":"https:\/\/media.api-sports.io\/football\/teams\/571.png"},"league":{"id":220,"name":"Cup","country":"Austria","logo":"https:\/\/media.api-sports.io\/football\/leagues\/220.png","flag":"https:\/\/media.api-sports.io\/flags\/at.svg","season":2021},"games":{"appearences":1,"lineups":1,"minutes":46,"number":null,"position":"Defender","rating":null,"captain":false},"substitutes":{"in":0,"out":1,"bench":0},"shots":{"total":null,"on":null},"goals":{"total":0,"conceded":null,"assists":null,"saves":null},"passes":{"total":null,"key":null,"accuracy":null},"tackles":{"total":null,"blocks":null,"interceptions":null},"duels":{"total":null,"won":null},"dribbles":{"attempts":null,"success":null,"past":null},"fouls":{"drawn":null,"committed":null},"cards":{"yellow":0,"yellowred":0,"red":0},"penalty":{"won":null,"commited":null,"scored":null,"missed":null,"saved":null}},{"team":{"id":571,"name":"Red Bull Salzburg","logo":"https:\/\/media.api-sports.io\/football\/teams\/571.png"},"league":{"id":2,"name":"UEFA Champions League","country":"World","logo":"https:\/\/media.api-sports.io\/football\/leagues\/2.png","flag":null,"season":2021},"games":{"appearences":0,"lineups":0,"minutes":0,"number":null,"position":"Defender","rating":null,"captain":false},"substitutes":{"in":0,"out":0,"bench":4},"shots":{"total":null,"on":null},"goals":{"total":0,"conceded":0,"assists":null,"saves":null},"passes":{"total":null,"key":null,"accuracy":null},"tackles":{"total":null,"blocks":null,"interceptions":null},"duels":{"total":null,"won":null},"dribbles":{"attempts":null,"success":null,"past":null},"fouls":{"drawn":null,"committed":null},"cards":{"yellow":0,"yellowred":0,"red":0},"penalty":{"won":null,"commited":null,"scored":0,"missed":0,"saved":null}},{"team":{"id":571,"name":"Red Bull Salzburg","logo":"https:\/\/media.api-sports.io\/football\/teams\/571.png"},"league":{"id":null,"name":"Club Friendlies","country":null,"logo":null,"flag":null,"season":"2021"},"games":{"appearences":2,"lineups":1,"minutes":90,"number":null,"position":"Defender","rating":null,"captain":false},"substitutes":{"in":1,"out":1,"bench":1},"shots":{"total":null,"on":null},"goals":{"total":0,"conceded":null,"assists":null,"saves":null},"passes":{"total":null,"key":null,"accuracy":null},"tackles":{"total":null,"blocks":null,"interceptions":null},"duels":{"total":null,"won":null},"dribbles":{"attempts":null,"success":null,"past":null},"fouls":{"drawn":null,"committed":null},"cards":{"yellow":0,"yellowred":0,"red":0},"penalty":{"won":null,"commited":null,"scored":null,"missed":null,"saved":null}}]},{"player":{"id":18964,"name":"Bernardo","firstname":"Bernardo","lastname":"Fernandes da Silva Junior","age":26,"birth":{"date":"1995-05-14","place":"S\u00e3o Paulo","country":"Brazil"},"nationality":"Brazil","height":"186 cm","weight":"76 kg","injured":false,"photo":"https:\/\/media.api-sports.io\/football\/players\/18964.png"},"statistics":[{"team":{"id":571,"name":"Red Bull Salzburg","logo":"https:\/\/media.api-sports.io\/football\/teams\/571.png"},"league":{"id":218,"name":"Tipp3 Bundesliga","country":"Austria","logo":"https:\/\/media.api-sports.io\/football\/leagues\/218.png","flag":"https:\/\/media.api-sports.io\/flags\/at.svg","season":2021},"games":{"appearences":10,"lineups":7,"minutes":537,"number":null,"position":"Defender","rating":"6.855555","captain":false},"substitutes":{"in":3,"out":2,"bench":4},"shots":{"total":3,"on":1},"goals":{"total":0,"conceded":0,"assists":1,"saves":null},"passes":{"total":391,"key":4,"accuracy":30},"tackles":{"total":12,"blocks":2,"interceptions":6},"duels":{"total":77,"won":46},"dribbles":{"attempts":5,"success":3,"past":null},"fouls":{"drawn":6,"committed":16},"cards":{"yellow":2,"yellowred":0,"red":0},"penalty":{"won":null,"commited":null,"scored":0,"missed":0,"saved":null}},{"team":{"id":571,"name":"Red Bull Salzburg","logo":"https:\/\/media.api-sports.io\/football\/teams\/571.png"},"league":{"id":220,"name":"Cup","country":"Austria","logo":"https:\/\/media.api-sports.io\/football\/leagues\/220.png","flag":"https:\/\/media.api-sports.io\/flags\/at.svg","season":2021},"games":{"appearences":2,"lineups":1,"minutes":81,"number":null,"position":"Defender","rating":null,"captain":false},"substitutes":{"in":1,"out":1,"bench":1},"shots":{"total":null,"on":null},"goals":{"total":1,"conceded":null,"assists":null,"saves":null},"passes":{"total":null,"key":null,"accuracy":null},"tackles":{"total":null,"blocks":null,"interceptions":null},"duels":{"total":null,"won":null},"dribbles":{"attempts":null,"success":null,"past":null},"fouls":{"drawn":null,"committed":null},"cards":{"yellow":0,"yellowred":0,"red":0},"penalty":{"won":null,"commited":null,"scored":null,"missed":null,"saved":null}},{"team":{"id":571,"name":"Red Bull Salzburg","logo":"https:\/\/media.api-sports.io\/football\/teams\/571.png"},"league":{"id":2,"name":"UEFA Champions League","country":"World","logo":"https:\/\/media.api-sports.io\/football\/leagues\/2.png","flag":null,"season":2021},"games":{"appearences":2,"lineups":0,"minutes":23,"number":null,"position":"Defender","rating":"6.800000","captain":false},"substitutes":{"in":2,"out":0,"bench":6},"shots":{"total":null,"on":null},"goals":{"total":0,"conceded":0,"assists":1,"saves":null},"passes":{"total":23,"key":1,"accuracy":9},"tackles":{"total":null,"blocks":1,"interceptions":1},"duels":{"total":3,"won":null},"dribbles":{"attempts":null,"success":null,"past":null},"fouls":{"drawn":null,"committed":null},"cards":{"yellow":0,"yellowred":0,"red":0},"penalty":{"won":null,"commited":null,"scored":0,"missed":0,"saved":null}},{"team":{"id":571,"name":"Red Bull Salzburg","logo":"https:\/\/media.api-sports.io\/football\/teams\/571.png"},"league":{"id":null,"name":"Club Friendlies","country":null,"logo":null,"flag":null,"season":"2021"},"games":{"appearences":0,"lineups":0,"minutes":0,"number":null,"position":"Defender","rating":null,"captain":false},"substitutes":{"in":0,"out":0,"bench":0},"shots":{"total":null,"on":null},"goals":{"total":0,"conceded":null,"assists":null,"saves":null},"passes":{"total":null,"key":null,"accuracy":null},"tackles":{"total":null,"blocks":null,"interceptions":null},"duels":{"total":null,"won":null},"dribbles":{"attempts":null,"success":null,"past":null},"fouls":{"drawn":null,"committed":null},"cards":{"yellow":0,"yellowred":0,"red":0},"penalty":{"won":null,"commited":null,"scored":null,"missed":null,"saved":null}}]},{"player":{"id":26507,"name":"N. Mantl","firstname":"Nico","lastname":"Mantl","age":21,"birth":{"date":"2000-02-06","place":"M\u00fcnchen","country":"Germany"},"nationality":"Germany","height":"193 cm","weight":"88 kg","injured":false,"photo":"https:\/\/media.api-sports.io\/football\/players\/26507.png"},"statistics":[{"team":{"id":571,"name":"Red Bull Salzburg","logo":"https:\/\/media.api-sports.io\/football\/teams\/571.png"},"league":{"id":218,"name":"Tipp3 Bundesliga","country":"Austria","logo":"https:\/\/media.api-sports.io\/football\/leagues\/218.png","flag":"https:\/\/media.api-sports.io\/flags\/at.svg","season":2021},"games":{"appearences":1,"lineups":1,"minutes":90,"number":null,"position":"Goalkeeper","rating":"6.700000","captain":false},"substitutes":{"in":0,"out":0,"bench":13},"shots":{"total":null,"on":null},"goals":{"total":0,"conceded":1,"assists":null,"saves":2},"passes":{"total":23,"key":null,"accuracy":18},"tackles":{"total":null,"blocks":null,"interceptions":null},"duels":{"total":null,"won":null},"dribbles":{"attempts":null,"success":null,"past":null},"fouls":{"drawn":null,"committed":null},"cards":{"yellow":0,"yellowred":0,"red":0},"penalty":{"won":null,"commited":null,"scored":0,"missed":0,"saved":1}},{"team":{"id":571,"name":"Red Bull Salzburg","logo":"https:\/\/media.api-sports.io\/football\/teams\/571.png"},"league":{"id":220,"name":"Cup","country":"Austria","logo":"https:\/\/media.api-sports.io\/football\/leagues\/220.png","flag":"https:\/\/media.api-sports.io\/flags\/at.svg","season":2021},"games":{"appearences":3,"lineups":3,"minutes":270,"number":null,"position":"Goalkeeper","rating":null,"captain":false},"substitutes":{"in":0,"out":0,"bench":0},"shots":{"total":null,"on":null},"goals":{"total":0,"conceded":null,"assists":null,"saves":null},"passes":{"total":null,"key":null,"accuracy":null},"tackles":{"total":null,"blocks":null,"interceptions":null},"duels":{"total":null,"won":null},"dribbles":{"attempts":null,"success":null,"past":null},"fouls":{"drawn":null,"committed":null},"cards":{"yellow":0,"yellowred":0,"red":0},"penalty":{"won":null,"commited":null,"scored":null,"missed":null,"saved":null}},{"team":{"id":571,"name":"Red Bull Salzburg","logo":"https:\/\/media.api-sports.io\/football\/teams\/571.png"},"league":{"id":2,"name":"UEFA Champions League","country":"World","logo":"https:\/\/media.api-sports.io\/football\/leagues\/2.png","flag":null,"season":2021},"games":{"appearences":0,"lineups":0,"minutes":0,"number":null,"position":"Goalkeeper","rating":null,"captain":false},"substitutes":{"in":0,"out":0,"bench":6},"shots":{"total":null,"on":null},"goals":{"total":0,"conceded":0,"assists":null,"saves":null},"passes":{"total":null,"key":null,"accuracy":null},"tackles":{"total":null,"blocks":null,"interceptions":null},"duels":{"total":null,"won":null},"dribbles":{"attempts":null,"success":null,"past":null},"fouls":{"drawn":null,"committed":null},"cards":{"yellow":0,"yellowred":0,"red":0},"penalty":{"won":null,"commited":null,"scored":0,"missed":0,"saved":0}},{"team":{"id":571,"name":"Red Bull Salzburg","logo":"https:\/\/media.api-sports.io\/football\/teams\/571.png"},"league":{"id":null,"name":"Club Friendlies","country":null,"logo":null,"flag":null,"season":"2021"},"games":{"appearences":1,"lineups":1,"minutes":46,"number":null,"position":"Goalkeeper","rating":null,"captain":false},"substitutes":{"in":0,"out":1,"bench":1},"shots":{"total":null,"on":null},"goals":{"total":0,"conceded":null,"assists":null,"saves":null},"passes":{"total":null,"key":null,"accuracy":null},"tackles":{"total":null,"blocks":null,"interceptions":null},"duels":{"total":null,"won":null},"dribbles":{"attempts":null,"success":null,"past":null},"fouls":{"drawn":null,"committed":null},"cards":{"yellow":0,"yellowred":0,"red":0},"penalty":{"won":null,"commited":null,"scored":null,"missed":null,"saved":null}}]},{"player":{"id":50726,"name":"Carlos Coronel","firstname":"Carlos Miguel","lastname":"Coronel","age":25,"birth":{"date":"1996-12-29","place":"Corumb\u00e1","country":"Brazil"},"nationality":"Brazil","height":"192 cm","weight":"88 kg","injured":false,"photo":"https:\/\/media.api-sports.io\/football\/players\/50726.png"},"statistics":[{"team":{"id":571,"name":"Red Bull Salzburg","logo":"https:\/\/media.api-sports.io\/football\/teams\/571.png"},"league":{"id":null,"name":"Club Friendlies","country":null,"logo":null,"flag":null,"season":"2021"},"games":{"appearences":0,"lineups":0,"minutes":0,"number":null,"position":"Goalkeeper","rating":null,"captain":false},"substitutes":{"in":0,"out":0,"bench":0},"shots":{"total":null,"on":null},"goals":{"total":0,"conceded":null,"assists":null,"saves":null},"passes":{"total":null,"key":null,"accuracy":null},"tackles":{"total":null,"blocks":null,"interceptions":null},"duels":{"total":null,"won":null},"dribbles":{"attempts":null,"success":null,"past":null},"fouls":{"drawn":null,"committed":null},"cards":{"yellow":0,"yellowred":0,"red":0},"penalty":{"won":null,"commited":null,"scored":null,"missed":null,"saved":null}}]},{"player":{"id":77623,"name":"Y. Diarra","firstname":"Hamacir\u00e9 Youba","lastname":"Diarra","age":23,"birth":{"date":"1998-03-24","place":null,"country":"Mali"},"nationality":"Mali","height":"178 cm","weight":"79 kg","injured":false,"photo":"https:\/\/media.api-sports.io\/football\/players\/77623.png"},"statistics":[{"team":{"id":571,"name":"Red Bull Salzburg","logo":"https:\/\/media.api-sports.io\/football\/teams\/571.png"},"league":{"id":null,"name":"Club Friendlies","country":null,"logo":null,"flag":null,"season":"2021"},"games":{"appearences":0,"lineups":0,"minutes":0,"number":null,"position":"Midfielder","rating":null,"captain":false},"substitutes":{"in":0,"out":0,"bench":0},"shots":{"total":null,"on":null},"goals":{"total":0,"conceded":null,"assists":null,"saves":null},"passes":{"total":null,"key":null,"accuracy":null},"tackles":{"total":null,"blocks":null,"interceptions":null},"duels":{"total":null,"won":null},"dribbles":{"attempts":null,"success":null,"past":null},"fouls":{"drawn":null,"committed":null},"cards":{"yellow":0,"yellowred":0,"red":0},"penalty":{"won":null,"commited":null,"scored":null,"missed":null,"saved":null}}]},{"player":{"id":119762,"name":"K. Pi\u0105tkowski","firstname":"Kamil","lastname":"Pi\u0105tkowski","age":21,"birth":{"date":"2000-06-21","place":null,"country":"Poland"},"nationality":"Poland","height":"191 cm","weight":"86 kg","injured":false,"photo":"https:\/\/media.api-sports.io\/football\/players\/119762.png"},"statistics":[{"team":{"id":571,"name":"Red Bull Salzburg","logo":"https:\/\/media.api-sports.io\/football\/teams\/571.png"},"league":{"id":218,"name":"Tipp3 Bundesliga","country":"Austria","logo":"https:\/\/media.api-sports.io\/football\/leagues\/218.png","flag":"https:\/\/media.api-sports.io\/flags\/at.svg","season":2021},"games":{"appearences":4,"lineups":3,"minutes":292,"number":null,"position":"Defender","rating":"7.150000","captain":false},"substitutes":{"in":1,"out":0,"bench":4},"shots":{"total":1,"on":null},"goals":{"total":0,"conceded":0,"assists":1,"saves":null},"passes":{"total":253,"key":2,"accuracy":55},"tackles":{"total":4,"blocks":null,"interceptions":5},"duels":{"total":26,"won":17},"dribbles":{"attempts":1,"success":1,"past":null},"fouls":{"drawn":5,"committed":2},"cards":{"yellow":0,"yellowred":0,"red":0},"penalty":{"won":null,"commited":null,"scored":0,"missed":0,"saved":null}},{"team":{"id":571,"name":"Red Bull Salzburg","logo":"https:\/\/media.api-sports.io\/football\/teams\/571.png"},"league":{"id":220,"name":"Cup","country":"Austria","logo":"https:\/\/media.api-sports.io\/football\/leagues\/220.png","flag":"https:\/\/media.api-sports.io\/flags\/at.svg","season":2021},"games":{"appearences":1,"lineups":1,"minutes":57,"number":null,"position":"Defender","rating":null,"captain":false},"substitutes":{"in":0,"out":1,"bench":0},"shots":{"total":null,"on":null},"goals":{"total":0,"conceded":null,"assists":null,"saves":null},"passes":{"total":null,"key":null,"accuracy":null},"tackles":{"total":null,"blocks":null,"interceptions":null},"duels":{"total":null,"won":null},"dribbles":{"attempts":null,"success":null,"past":null},"fouls":{"drawn":null,"committed":null},"cards":{"yellow":0,"yellowred":0,"red":0},"penalty":{"won":null,"commited":null,"scored":null,"missed":null,"saved":null}},{"team":{"id":571,"name":"Red Bull Salzburg","logo":"https:\/\/media.api-sports.io\/football\/teams\/571.png"},"league":{"id":2,"name":"UEFA Champions League","country":"World","logo":"https:\/\/media.api-sports.io\/football\/leagues\/2.png","flag":null,"season":2021},"games":{"appearences":1,"lineups":0,"minutes":39,"number":null,"position":"Defender","rating":"6.700000","captain":false},"substitutes":{"in":1,"out":0,"bench":3},"shots":{"total":null,"on":null},"goals":{"total":0,"conceded":0,"assists":null,"saves":null},"passes":{"total":30,"key":null,"accuracy":28},"tackles":{"total":1,"blocks":1,"interceptions":null},"duels":{"total":7,"won":2},"dribbles":{"attempts":null,"success":null,"past":null},"fouls":{"drawn":1,"committed":null},"cards":{"yellow":0,"yellowred":0,"red":0},"penalty":{"won":null,"commited":null,"scored":0,"missed":0,"saved":null}},{"team":{"id":571,"name":"Red Bull Salzburg","logo":"https:\/\/media.api-sports.io\/football\/teams\/571.png"},"league":{"id":null,"name":"Club Friendlies","country":null,"logo":null,"flag":null,"season":"2021"},"games":{"appearences":2,"lineups":1,"minutes":89,"number":null,"position":"Defender","rating":null,"captain":false},"substitutes":{"in":1,"out":2,"bench":1},"shots":{"total":null,"on":null},"goals":{"total":0,"conceded":null,"assists":null,"saves":null},"passes":{"total":null,"key":null,"accuracy":null},"tackles":{"total":null,"blocks":null,"interceptions":null},"duels":{"total":null,"won":null},"dribbles":{"attempts":null,"success":null,"past":null},"fouls":{"drawn":null,"committed":null},"cards":{"yellow":0,"yellowred":0,"red":0},"penalty":{"won":null,"commited":null,"scored":null,"missed":null,"saved":null}}]},{"player":{"id":237116,"name":"S. Tijani","firstname":"Samson Okikiola","lastname":"Tijani","age":19,"birth":{"date":"2002-05-17","place":null,"country":"Nigeria"},"nationality":"Nigeria","height":"170 cm","weight":"63 kg","injured":false,"photo":"https:\/\/media.api-sports.io\/football\/players\/237116.png"},"statistics":[{"team":{"id":571,"name":"Red Bull Salzburg","logo":"https:\/\/media.api-sports.io\/football\/teams\/571.png"},"league":{"id":220,"name":"Cup","country":"Austria","logo":"https:\/\/media.api-sports.io\/football\/leagues\/220.png","flag":"https:\/\/media.api-sports.io\/flags\/at.svg","season":2021},"games":{"appearences":0,"lineups":0,"minutes":0,"number":null,"position":"Midfielder","rating":null,"captain":false},"substitutes":{"in":0,"out":0,"bench":0},"shots":{"total":null,"on":null},"goals":{"total":0,"conceded":null,"assists":null,"saves":null},"passes":{"total":null,"key":null,"accuracy":null},"tackles":{"total":null,"blocks":null,"interceptions":null},"duels":{"total":null,"won":null},"dribbles":{"attempts":null,"success":null,"past":null},"fouls":{"drawn":null,"committed":null},"cards":{"yellow":0,"yellowred":0,"red":0},"penalty":{"won":null,"commited":null,"scored":null,"missed":null,"saved":null}},{"team":{"id":571,"name":"Red Bull Salzburg","logo":"https:\/\/media.api-sports.io\/football\/teams\/571.png"},"league":{"id":null,"name":"Club Friendlies","country":null,"logo":null,"flag":null,"season":"2021"},"games":{"appearences":0,"lineups":0,"minutes":0,"number":null,"position":"Midfielder","rating":null,"captain":false},"substitutes":{"in":0,"out":0,"bench":0},"shots":{"total":null,"on":null},"goals":{"total":0,"conceded":null,"assists":null,"saves":null},"passes":{"total":null,"key":null,"accuracy":null},"tackles":{"total":null,"blocks":null,"interceptions":null},"duels":{"total":null,"won":null},"dribbles":{"attempts":null,"success":null,"past":null},"fouls":{"drawn":null,"committed":null},"cards":{"yellow":0,"yellowred":0,"red":0},"penalty":{"won":null,"commited":null,"scored":null,"missed":null,"saved":null}}]},{"player":{"id":302868,"name":"D. Guindo","firstname":"Daouda","lastname":"Guindo","age":19,"birth":{"date":"2002-10-14","place":null,"country":"Mali"},"nationality":"Mali","height":"183 cm","weight":null,"injured":false,"photo":"https:\/\/media.api-sports.io\/football\/players\/302868.png"},"statistics":[{"team":{"id":571,"name":"Red Bull Salzburg","logo":"https:\/\/media.api-sports.io\/football\/teams\/571.png"},"league":{"id":218,"name":"Tipp3 Bundesliga","country":"Austria","logo":"https:\/\/media.api-sports.io\/football\/leagues\/218.png","flag":"https:\/\/media.api-sports.io\/flags\/at.svg","season":2021},"games":{"appearences":5,"lineups":0,"minutes":28,"number":null,"position":"Defender","rating":"6.750000","captain":false},"substitutes":{"in":5,"out":0,"bench":8},"shots":{"total":null,"on":null},"goals":{"total":0,"conceded":0,"assists":null,"saves":null},"passes":{"total":14,"key":null,"accuracy":2},"tackles":{"total":2,"blocks":1,"interceptions":3},"duels":{"total":5,"won":3},"dribbles":{"attempts":null,"success":null,"past":null},"fouls":{"drawn":null,"committed":null},"cards":{"yellow":0,"yellowred":0,"red":0},"penalty":{"won":null,"commited":null,"scored":0,"missed":0,"saved":null}},{"team":{"id":571,"name":"Red Bull Salzburg","logo":"https:\/\/media.api-sports.io\/football\/teams\/571.png"},"league":{"id":220,"name":"Cup","country":"Austria","logo":"https:\/\/media.api-sports.io\/football\/leagues\/220.png","flag":"https:\/\/media.api-sports.io\/flags\/at.svg","season":2021},"games":{"appearences":3,"lineups":2,"minutes":189,"number":null,"position":"Defender","rating":null,"captain":false},"substitutes":{"in":1,"out":1,"bench":1},"shots":{"total":null,"on":null},"goals":{"total":1,"conceded":null,"assists":null,"saves":null},"passes":{"total":null,"key":null,"accuracy":null},"tackles":{"total":null,"blocks":null,"interceptions":null},"duels":{"total":null,"won":null},"dribbles":{"attempts":null,"success":null,"past":null},"fouls":{"drawn":null,"committed":null},"cards":{"yellow":0,"yellowred":0,"red":0},"penalty":{"won":null,"commited":null,"scored":null,"missed":null,"saved":null}},{"team":{"id":571,"name":"Red Bull Salzburg","logo":"https:\/\/media.api-sports.io\/football\/teams\/571.png"},"league":{"id":2,"name":"UEFA Champions League","country":"World","logo":"https:\/\/media.api-sports.io\/football\/leagues\/2.png","flag":null,"season":2021},"games":{"appearences":1,"lineups":0,"minutes":4,"number":null,"position":"Defender","rating":"6.700000","captain":false},"substitutes":{"in":1,"out":0,"bench":6},"shots":{"total":null,"on":null},"goals":{"total":0,"conceded":0,"assists":null,"saves":null},"passes":{"total":6,"key":null,"accuracy":6},"tackles":{"total":null,"blocks":null,"interceptions":1},"duels":{"total":null,"won":null},"dribbles":{"attempts":null,"success":null,"past":null},"fouls":{"drawn":null,"committed":null},"cards":{"yellow":0,"yellowred":0,"red":0},"penalty":{"won":null,"commited":null,"scored":0,"missed":0,"saved":null}},{"team":{"id":571,"name":"Red Bull Salzburg","logo":"https:\/\/media.api-sports.io\/football\/teams\/571.png"},"league":{"id":null,"name":"Club Friendlies","country":null,"logo":null,"flag":null,"season":"2021"},"games":{"appearences":2,"lineups":1,"minutes":105,"number":null,"position":"Defender","rating":null,"captain":false},"substitutes":{"in":1,"out":1,"bench":1},"shots":{"total":null,"on":null},"goals":{"total":0,"conceded":null,"assists":null,"saves":null},"passes":{"total":null,"key":null,"accuracy":null},"tackles":{"total":null,"blocks":null,"interceptions":null},"duels":{"total":null,"won":null},"dribbles":{"attempts":null,"success":null,"past":null},"fouls":{"drawn":null,"committed":null},"cards":{"yellow":0,"yellowred":0,"red":0},"penalty":{"won":null,"commited":null,"scored":null,"missed":null,"saved":null}}]},{"player":{"id":303949,"name":"L. V\u00e1squez","firstname":"Luis Fernando","lastname":"V\u00e1squez D\u00edaz","age":18,"birth":{"date":"2003-01-03","place":null,"country":"Colombia"},"nationality":"Colombia","height":"192 cm","weight":null,"injured":false,"photo":"https:\/\/media.api-sports.io\/football\/players\/303949.png"},"statistics":[{"team":{"id":571,"name":"Red Bull Salzburg","logo":"https:\/\/media.api-sports.io\/football\/teams\/571.png"},"league":{"id":null,"name":"Club Friendlies","country":null,"logo":null,"flag":null,"season":"2021"},"games":{"appearences":0,"lineups":0,"minutes":0,"number":null,"position":"Defender","rating":null,"captain":false},"substitutes":{"in":0,"out":0,"bench":0},"shots":{"total":null,"on":null},"goals":{"total":0,"conceded":null,"assists":null,"saves":null},"passes":{"total":null,"key":null,"accuracy":null},"tackles":{"total":null,"blocks":null,"interceptions":null},"duels":{"total":null,"won":null},"dribbles":{"attempts":null,"success":null,"past":null},"fouls":{"drawn":null,"committed":null},"cards":{"yellow":0,"yellowred":0,"red":0},"penalty":{"won":null,"commited":null,"scored":null,"missed":null,"saved":null}}]},{"player":{"id":304026,"name":"F. Amankwah","firstname":"Forson","lastname":"Amankwah","age":19,"birth":{"date":"2002-12-31","place":null,"country":"Ghana"},"nationality":"Ghana","height":"173 cm","weight":null,"injured":false,"photo":"https:\/\/media.api-sports.io\/football\/players\/304026.png"},"statistics":[{"team":{"id":571,"name":"Red Bull Salzburg","logo":"https:\/\/media.api-sports.io\/football\/teams\/571.png"},"league":{"id":null,"name":"Club Friendlies","country":null,"logo":null,"flag":null,"season":"2021"},"games":{"appearences":2,"lineups":0,"minutes":3,"number":null,"position":"Midfielder","rating":null,"captain":false},"substitutes":{"in":2,"out":0,"bench":2},"shots":{"total":null,"on":null},"goals":{"total":0,"conceded":null,"assists":null,"saves":null},"passes":{"total":null,"key":null,"accuracy":null},"tackles":{"total":null,"blocks":null,"interceptions":null},"duels":{"total":null,"won":null},"dribbles":{"attempts":null,"success":null,"past":null},"fouls":{"drawn":null,"committed":null},"cards":{"yellow":0,"yellowred":0,"red":0},"penalty":{"won":null,"commited":null,"scored":null,"missed":null,"saved":null}}]},{"player":{"id":304315,"name":"D. Owusu","firstname":"Daniel","lastname":"Owusu","age":18,"birth":{"date":"2003-01-25","place":null,"country":"Ghana"},"nationality":"Ghana","height":"183 cm","weight":null,"injured":false,"photo":"https:\/\/media.api-sports.io\/football\/players\/304315.png"},"statistics":[{"team":{"id":571,"name":"Red Bull Salzburg","logo":"https:\/\/media.api-sports.io\/football\/teams\/571.png"},"league":{"id":null,"name":"Club Friendlies","country":null,"logo":null,"flag":null,"season":"2021"},"games":{"appearences":0,"lineups":0,"minutes":0,"number":null,"position":"Attacker","rating":null,"captain":false},"substitutes":{"in":0,"out":0,"bench":0},"shots":{"total":null,"on":null},"goals":{"total":0,"conceded":null,"assists":null,"saves":null},"passes":{"total":null,"key":null,"accuracy":null},"tackles":{"total":null,"blocks":null,"interceptions":null},"duels":{"total":null,"won":null},"dribbles":{"attempts":null,"success":null,"past":null},"fouls":{"drawn":null,"committed":null},"cards":{"yellow":0,"yellowred":0,"red":0},"penalty":{"won":null,"commited":null,"scored":null,"missed":null,"saved":null}}]}]}